[
  {
    "timestamp": "2025-08-20T23:20:18.906525",
    "symbol": "ETHUSDT",
    "trigger": "ENTRADA_CAPITAL",
    "data": {
      "symbol": "ETHUSDT",
      "current_price": 4288.67,
      "price_change_24h": 3.819,
      "volume_24h": 2945458487.505496,
      "rsi_value": 57.95797516714421,
      "rsi_signal": "57.96",
      "bollinger_signal": "Nenhum",
      "macd_signal": "Nenhum",
      "mme_cross": "Nenhum",
      "hilo_signal": "Nenhum",
      "market_cap": 72211
    }
  },
  {
    "timestamp": "2025-08-19T13:18:11.752880",
    "symbol": "ETHUSDT",
    "trigger": "FUGA_CAPITAL",
    "data": {
      "symbol": "ETHUSDT",
      "current_price": 4182.84,
      "price_change_24h": -3.445,
      "volume_24h": 2933854808.912853,
      "rsi_value": 33.28896103896115,
      "rsi_signal": "33.29",
      "bollinger_signal": "Nenhum",
      "macd_signal": "Nenhum",
      "mme_cross": "Nenhum",
      "hilo_signal": "Nenhum",
      "market_cap": 82193
    }
  },
  {
    "timestamp": "2025-08-19T13:18:11.146388",
    "symbol": "BTCUSDT",
    "trigger": "RSI_SOBREVENDA",
    "data": {
      "symbol": "BTCUSDT",
      "current_price": 113760.0,
      "price_change_24h": -1.982,
      "volume_24h": 1693797309.2729318,
      "rsi_value": 26.98514916850651,
      "rsi_signal": "26.99",
      "bollinger_signal": "Nenhum",
      "macd_signal": "Nenhum",
      "mme_cross": "Nenhum",
      "hilo_signal": "Nenhum",
      "market_cap": 12884095
    }
  },
  {
    "timestamp": "2025-08-19T13:13:08.430319",
    "symbol": "ETHUSDT",
    "trigger": "FUGA_CAPITAL",
    "data": {
      "symbol": "ETHUSDT",
      "current_price": 4205.51,
      "price_change_24h": -3.423,
      "volume_24h": 2973643129.02689,
      "rsi_value": 36.31998961915265,
      "rsi_signal": "36.32",
      "bollinger_signal": "Nenhum",
      "macd_signal": "Nenhum",
      "mme_cross": "Nenhum",
      "hilo_signal": "Nenhum",
      "market_cap": 82587
    }
  },
  {
    "timestamp": "2025-08-19T13:13:08.227452",
    "symbol": "BTCUSDT",
    "trigger": "FUGA_CAPITAL",
    "data": {
      "symbol": "BTCUSDT",
      "current_price": 113836.26,
      "price_change_24h": -2.131,
      "volume_24h": 1695132846.2078667,
      "rsi_value": 27.48967661114476,
      "rsi_signal": "27.49",
      "bollinger_signal": "Nenhum",
      "macd_signal": "Nenhum",
      "mme_cross": "Nenhum",
      "hilo_signal": "Nenhum",
      "market_cap": 12869861
    }
  },
  {
    "timestamp": "2025-08-19T13:13:08.227181",
    "symbol": "BTCUSDT",
    "trigger": "RSI_SOBREVENDA",
    "data": {
      "symbol": "BTCUSDT",
      "current_price": 113836.26,
      "price_change_24h": -2.131,
      "volume_24h": 1695132846.2078667,
      "rsi_value": 27.48967661114476,
      "rsi_signal": "27.49",
      "bollinger_signal": "Nenhum",
      "macd_signal": "Nenhum",
      "mme_cross": "Nenhum",
      "hilo_signal": "Nenhum",
      "market_cap": 12869861
    }
  },
  {
    "timestamp": "2025-08-19T13:07:33.693726",
    "symbol": "ETHUSDT",
    "trigger": "FUGA_CAPITAL",
    "data": {
      "symbol": "ETHUSDT",
      "current_price": 4200.18,
      "price_change_24h": -3.578,
      "volume_24h": 2976995803.311575,
      "rsi_value": 36.156372979477666,
      "rsi_signal": "36.16",
      "bollinger_signal": "Nenhum",
      "macd_signal": "Nenhum",
      "mme_cross": "Nenhum",
      "hilo_signal": "Nenhum",
      "market_cap": 82204
    }
  },
  {
    "timestamp": "2025-08-19T13:07:33.693281",
    "symbol": "ETHUSDT",
    "trigger": "PRECO_ACIMA",
    "data": {
      "symbol": "ETHUSDT",
      "current_price": 4200.18,
      "price_change_24h": -3.578,
      "volume_24h": 2976995803.311575,
      "rsi_value": 36.156372979477666,
      "rsi_signal": "36.16",
      "bollinger_signal": "Nenhum",
      "macd_signal": "Nenhum",
      "mme_cross": "Nenhum",
      "hilo_signal": "Nenhum",
      "market_cap": 82204
    }
  },
  {
    "timestamp": "2025-08-19T13:07:33.285953",
    "symbol": "BTCUSDT",
    "trigger": "FUGA_CAPITAL",
    "data": {
      "symbol": "BTCUSDT",
      "current_price": 113800.0,
      "price_change_24h": -2.08,
      "volume_24h": 1692171662.9627838,
      "rsi_value": 27.381690864018623,
      "rsi_signal": "27.38",
      "bollinger_signal": "Nenhum",
      "macd_signal": "Nenhum",
      "mme_cross": "Nenhum",
      "hilo_signal": "Nenhum",
      "market_cap": 12884024
    }
  },
  {
    "timestamp": "2025-08-19T13:07:33.285614",
    "symbol": "BTCUSDT",
    "trigger": "RSI_SOBREVENDA",
    "data": {
      "symbol": "BTCUSDT",
      "current_price": 113800.0,
      "price_change_24h": -2.08,
      "volume_24h": 1692171662.9627838,
      "rsi_value": 27.381690864018623,
      "rsi_signal": "27.38",
      "bollinger_signal": "Nenhum",
      "macd_signal": "Nenhum",
      "mme_cross": "Nenhum",
      "hilo_signal": "Nenhum",
      "market_cap": 12884024
    }
  },
  {
    "timestamp": "2025-08-19T13:07:32.651624",
    "symbol": "AAVEUSDT",
    "trigger": "FUGA_CAPITAL",
    "data": {
      "symbol": "AAVEUSDT",
      "current_price": 281.54,
      "price_change_24h": -3.321,
      "volume_24h": 31734484.66057,
      "rsi_value": 42.74558158651864,
      "rsi_signal": "42.75",
      "bollinger_signal": "Nenhum",
      "macd_signal": "Nenhum",
      "mme_cross": "Nenhum",
      "hilo_signal": "Nenhum",
      "market_cap": 4274343996
    }
  },
  {
    "timestamp": "2025-08-19T13:02:58.560457",
    "symbol": "ETHUSDT",
    "trigger": "FUGA_CAPITAL",
    "data": {
      "symbol": "ETHUSDT",
      "current_price": 4191.76,
      "price_change_24h": -3.528,
      "volume_24h": 2976838094.947215,
      "rsi_value": 34.16869397140671,
      "rsi_signal": "34.17",
      "bollinger_signal": "Nenhum",
      "macd_signal": "Nenhum",
      "mme_cross": "Nenhum",
      "market_cap": 82204
    }
  },
  {
    "timestamp": "2025-08-19T13:02:58.560171",
    "symbol": "ETHUSDT",
    "trigger": "PRECO_ACIMA",
    "data": {
      "symbol": "ETHUSDT",
      "current_price": 4191.76,
      "price_change_24h": -3.528,
      "volume_24h": 2976838094.947215,
      "rsi_value": 34.16869397140671,
      "rsi_signal": "34.17",
      "bollinger_signal": "Nenhum",
      "macd_signal": "Nenhum",
      "mme_cross": "Nenhum",
      "market_cap": 82204
    }
  },
  {
    "timestamp": "2025-08-19T13:02:58.158319",
    "symbol": "BTCUSDT",
    "trigger": "FUGA_CAPITAL",
    "data": {
      "symbol": "BTCUSDT",
      "current_price": 113844.01,
      "price_change_24h": -2.053,
      "volume_24h": 1685065924.4552114,
      "rsi_value": 28.11652664671975,
      "rsi_signal": "28.12",
      "bollinger_signal": "Nenhum",
      "macd_signal": "Nenhum",
      "mme_cross": "Nenhum",
      "market_cap": 12884024
    }
  },
  {
    "timestamp": "2025-08-19T13:02:58.157959",
    "symbol": "BTCUSDT",
    "trigger": "RSI_SOBREVENDA",
    "data": {
      "symbol": "BTCUSDT",
      "current_price": 113844.01,
      "price_change_24h": -2.053,
      "volume_24h": 1685065924.4552114,
      "rsi_value": 28.11652664671975,
      "rsi_signal": "28.12",
      "bollinger_signal": "Nenhum",
      "macd_signal": "Nenhum",
      "mme_cross": "Nenhum",
      "market_cap": 12884024
    }
  },
  {
    "timestamp": "2025-08-19T13:02:57.530576",
    "symbol": "AAVEUSDT",
    "trigger": "FUGA_CAPITAL",
    "data": {
      "symbol": "AAVEUSDT",
      "current_price": 281.29,
      "price_change_24h": -3.194,
      "volume_24h": 32008322.75596,
      "rsi_value": 41.837160751565705,
      "rsi_signal": "41.84",
      "bollinger_signal": "Nenhum",
      "macd_signal": "Nenhum",
      "mme_cross": "Nenhum",
      "market_cap": 4266255296
    }
  },
  {
    "timestamp": "2025-08-19T12:08:58.231025",
    "symbol": "SOLUSDT",
    "trigger": "CRUZAMENTO_MACD_BAIXA",
    "data": {
      "symbol": "SOLUSDT",
      "current_price": 178.22,
      "price_change_24h": -2.028,
      "volume_24h": 516837855.38661,
      "rsi_value": 32.24637681159416,
      "rsi_signal": "32.25",
      "bollinger_signal": "Nenhum",
      "macd_signal": "Cruzamento de Baixa",
      "mme_cross": "Nenhum",
      "market_cap": 0.0
    }
  },
  {
    "timestamp": "2025-08-19T12:08:57.825879",
    "symbol": "ETHUSDT",
    "trigger": "FUGA_CAPITAL",
    "data": {
      "symbol": "ETHUSDT",
      "current_price": 4189.09,
      "price_change_24h": -2.936,
      "volume_24h": 2838148665.810511,
      "rsi_value": 32.74893234434714,
      "rsi_signal": "32.75",
      "bollinger_signal": "Nenhum",
      "macd_signal": "Cruzamento de Baixa",
      "mme_cross": "Nenhum",
      "market_cap": 82504
    }
  },
  {
    "timestamp": "2025-08-19T12:08:57.825636",
    "symbol": "ETHUSDT",
    "trigger": "CRUZAMENTO_MACD_BAIXA",
    "data": {
      "symbol": "ETHUSDT",
      "current_price": 4189.09,
      "price_change_24h": -2.936,
      "volume_24h": 2838148665.810511,
      "rsi_value": 32.74893234434714,
      "rsi_signal": "32.75",
      "bollinger_signal": "Nenhum",
      "macd_signal": "Cruzamento de Baixa",
      "mme_cross": "Nenhum",
      "market_cap": 82504
    }
  },
  {
    "timestamp": "2025-08-19T12:08:57.825294",
    "symbol": "ETHUSDT",
    "trigger": "PRECO_ACIMA",
    "data": {
      "symbol": "ETHUSDT",
      "current_price": 4189.09,
      "price_change_24h": -2.936,
      "volume_24h": 2838148665.810511,
      "rsi_value": 32.74893234434714,
      "rsi_signal": "32.75",
      "bollinger_signal": "Nenhum",
      "macd_signal": "Cruzamento de Baixa",
      "mme_cross": "Nenhum",
      "market_cap": 82504
    }
  },
  {
    "timestamp": "2025-08-19T12:08:57.219113",
    "symbol": "BTCUSDT",
    "trigger": "PRECO_ABAIXO_BANDA_INFERIOR",
    "data": {
      "symbol": "BTCUSDT",
      "current_price": 113806.01,
      "price_change_24h": -1.431,
      "volume_24h": 1636031990.3856127,
      "rsi_value": 26.87886479003255,
      "rsi_signal": "26.88",
      "bollinger_signal": "Abaixo da Banda",
      "macd_signal": "Nenhum",
      "mme_cross": "Nenhum",
      "market_cap": 12903471
    }
  },
  {
    "timestamp": "2025-08-19T12:08:57.218676",
    "symbol": "BTCUSDT",
    "trigger": "RSI_SOBREVENDA",
    "data": {
      "symbol": "BTCUSDT",
      "current_price": 113806.01,
      "price_change_24h": -1.431,
      "volume_24h": 1636031990.3856127,
      "rsi_value": 26.87886479003255,
      "rsi_signal": "26.88",
      "bollinger_signal": "Abaixo da Banda",
      "macd_signal": "Nenhum",
      "mme_cross": "Nenhum",
      "market_cap": 12903471
    }
  },
  {
    "timestamp": "2025-08-19T12:08:56.614259",
    "symbol": "AAVEUSDT",
    "trigger": "FUGA_CAPITAL",
    "data": {
      "symbol": "AAVEUSDT",
      "current_price": 279.47,
      "price_change_24h": -3.016,
      "volume_24h": 31120640.11443,
      "rsi_value": 34.96031746031748,
      "rsi_signal": "34.96",
      "bollinger_signal": "Nenhum",
      "macd_signal": "Cruzamento de Baixa",
      "mme_cross": "Nenhum",
      "market_cap": 4260682749
    }
  },
  {
    "timestamp": "2025-08-19T12:08:56.613818",
    "symbol": "AAVEUSDT",
    "trigger": "CRUZAMENTO_MACD_BAIXA",
    "data": {
      "symbol": "AAVEUSDT",
      "current_price": 279.47,
      "price_change_24h": -3.016,
      "volume_24h": 31120640.11443,
      "rsi_value": 34.96031746031748,
      "rsi_signal": "34.96",
      "bollinger_signal": "Nenhum",
      "macd_signal": "Cruzamento de Baixa",
      "mme_cross": "Nenhum",
      "market_cap": 4260682749
    }
  },
  {
    "timestamp": "2025-08-19T12:03:54.965883",
    "symbol": "SOLUSDT",
    "trigger": "CRUZAMENTO_MACD_BAIXA",
    "data": {
      "symbol": "SOLUSDT",
      "current_price": 178.87,
      "price_change_24h": -1.951,
      "volume_24h": 509769721.73464,
      "rsi_value": 34.54810495626829,
      "rsi_signal": "34.55",
      "bollinger_signal": "Nenhum",
      "macd_signal": "Cruzamento de Baixa",
      "mme_cross": "Nenhum",
      "market_cap": 0.0
    }
  },
  {
    "timestamp": "2025-08-19T12:03:54.563297",
    "symbol": "ETHUSDT",
    "trigger": "FUGA_CAPITAL",
    "data": {
      "symbol": "ETHUSDT",
      "current_price": 4193.55,
      "price_change_24h": -3.049,
      "volume_24h": 2799593574.885551,
      "rsi_value": 33.36566440349186,
      "rsi_signal": "33.37",
      "bollinger_signal": "Nenhum",
      "macd_signal": "Cruzamento de Baixa",
      "mme_cross": "Nenhum",
      "market_cap": 82830
    }
  },
  {
    "timestamp": "2025-08-19T12:03:54.563074",
    "symbol": "ETHUSDT",
    "trigger": "CRUZAMENTO_MACD_BAIXA",
    "data": {
      "symbol": "ETHUSDT",
      "current_price": 4193.55,
      "price_change_24h": -3.049,
      "volume_24h": 2799593574.885551,
      "rsi_value": 33.36566440349186,
      "rsi_signal": "33.37",
      "bollinger_signal": "Nenhum",
      "macd_signal": "Cruzamento de Baixa",
      "mme_cross": "Nenhum",
      "market_cap": 82830
    }
  },
  {
    "timestamp": "2025-08-19T12:03:54.562612",
    "symbol": "ETHUSDT",
    "trigger": "PRECO_ACIMA",
    "data": {
      "symbol": "ETHUSDT",
      "current_price": 4193.55,
      "price_change_24h": -3.049,
      "volume_24h": 2799593574.885551,
      "rsi_value": 33.36566440349186,
      "rsi_signal": "33.37",
      "bollinger_signal": "Nenhum",
      "macd_signal": "Cruzamento de Baixa",
      "mme_cross": "Nenhum",
      "market_cap": 82830
    }
  },
  {
    "timestamp": "2025-08-19T12:03:53.955383",
    "symbol": "BTCUSDT",
    "trigger": "RSI_SOBREVENDA",
    "data": {
      "symbol": "BTCUSDT",
      "current_price": 113975.58,
      "price_change_24h": -1.376,
      "volume_24h": 1591233682.8207507,
      "rsi_value": 28.995279060975932,
      "rsi_signal": "29.00",
      "bollinger_signal": "Nenhum",
      "macd_signal": "Nenhum",
      "mme_cross": "Nenhum",
      "market_cap": 12903471
    }
  },
  {
    "timestamp": "2025-08-19T12:03:53.340495",
    "symbol": "AAVEUSDT",
    "trigger": "FUGA_CAPITAL",
    "data": {
      "symbol": "AAVEUSDT",
      "current_price": 279.78,
      "price_change_24h": -3.351,
      "volume_24h": 31088315.06161,
      "rsi_value": 35.46698872785825,
      "rsi_signal": "35.47",
      "bollinger_signal": "Nenhum",
      "macd_signal": "Cruzamento de Baixa",
      "mme_cross": "Nenhum",
      "market_cap": 4268713230
    }
  },
  {
    "timestamp": "2025-08-19T12:03:53.340087",
    "symbol": "AAVEUSDT",
    "trigger": "CRUZAMENTO_MACD_BAIXA",
    "data": {
      "symbol": "AAVEUSDT",
      "current_price": 279.78,
      "price_change_24h": -3.351,
      "volume_24h": 31088315.06161,
      "rsi_value": 35.46698872785825,
      "rsi_signal": "35.47",
      "bollinger_signal": "Nenhum",
      "macd_signal": "Cruzamento de Baixa",
      "mme_cross": "Nenhum",
      "market_cap": 4268713230
    }
  },
  {
    "timestamp": "2025-08-19T11:58:51.624162",
    "symbol": "SOLUSDT",
    "trigger": "RSI_SOBREVENDA",
    "data": {
      "symbol": "SOLUSDT",
      "current_price": 178.6,
      "price_change_24h": -2.062,
      "volume_24h": 504617588.06795,
      "rsi_value": 29.065969954278216,
      "rsi_signal": "29.07",
      "bollinger_signal": "Nenhum",
      "macd_signal": "Nenhum",
      "mme_cross": "Nenhum",
      "market_cap": 0.0
    }
  },
  {
    "timestamp": "2025-08-19T11:58:50.812698",
    "symbol": "ETHUSDT",
    "trigger": "FUGA_CAPITAL",
    "data": {
      "symbol": "ETHUSDT",
      "current_price": 4193.3,
      "price_change_24h": -3.145,
      "volume_24h": 2784801851.828056,
      "rsi_value": 28.86536665440245,
      "rsi_signal": "28.87",
      "bollinger_signal": "Nenhum",
      "macd_signal": "Nenhum",
      "mme_cross": "Nenhum",
      "market_cap": 82830
    }
  },
  {
    "timestamp": "2025-08-19T11:58:50.812479",
    "symbol": "ETHUSDT",
    "trigger": "RSI_SOBREVENDA",
    "data": {
      "symbol": "ETHUSDT",
      "current_price": 4193.3,
      "price_change_24h": -3.145,
      "volume_24h": 2784801851.828056,
      "rsi_value": 28.86536665440245,
      "rsi_signal": "28.87",
      "bollinger_signal": "Nenhum",
      "macd_signal": "Nenhum",
      "mme_cross": "Nenhum",
      "market_cap": 82830
    }
  },
  {
    "timestamp": "2025-08-19T11:58:50.812178",
    "symbol": "ETHUSDT",
    "trigger": "PRECO_ACIMA",
    "data": {
      "symbol": "ETHUSDT",
      "current_price": 4193.3,
      "price_change_24h": -3.145,
      "volume_24h": 2784801851.828056,
      "rsi_value": 28.86536665440245,
      "rsi_signal": "28.87",
      "bollinger_signal": "Nenhum",
      "macd_signal": "Nenhum",
      "mme_cross": "Nenhum",
      "market_cap": 82830
    }
  },
  {
    "timestamp": "2025-08-19T11:58:50.403816",
    "symbol": "BTCUSDT",
    "trigger": "CRUZAMENTO_MACD_BAIXA",
    "data": {
      "symbol": "BTCUSDT",
      "current_price": 113943.94,
      "price_change_24h": -1.421,
      "volume_24h": 1571701570.3327534,
      "rsi_value": 23.53845687556219,
      "rsi_signal": "23.54",
      "bollinger_signal": "Abaixo da Banda",
      "macd_signal": "Cruzamento de Baixa",
      "mme_cross": "Nenhum",
      "market_cap": 12903471
    }
  },
  {
    "timestamp": "2025-08-19T11:58:50.403550",
    "symbol": "BTCUSDT",
    "trigger": "PRECO_ABAIXO_BANDA_INFERIOR",
    "data": {
      "symbol": "BTCUSDT",
      "current_price": 113943.94,
      "price_change_24h": -1.421,
      "volume_24h": 1571701570.3327534,
      "rsi_value": 23.53845687556219,
      "rsi_signal": "23.54",
      "bollinger_signal": "Abaixo da Banda",
      "macd_signal": "Cruzamento de Baixa",
      "mme_cross": "Nenhum",
      "market_cap": 12903471
    }
  },
  {
    "timestamp": "2025-08-19T11:58:50.403200",
    "symbol": "BTCUSDT",
    "trigger": "RSI_SOBREVENDA",
    "data": {
      "symbol": "BTCUSDT",
      "current_price": 113943.94,
      "price_change_24h": -1.421,
      "volume_24h": 1571701570.3327534,
      "rsi_value": 23.53845687556219,
      "rsi_signal": "23.54",
      "bollinger_signal": "Abaixo da Banda",
      "macd_signal": "Cruzamento de Baixa",
      "mme_cross": "Nenhum",
      "market_cap": 12903471
    }
  },
  {
    "timestamp": "2025-08-19T11:50:16.834651",
    "symbol": "SOLUSDT",
    "trigger": "RSI_SOBREVENDA",
    "data": {
      "symbol": "SOLUSDT",
      "current_price": 178.51,
      "price_change_24h": -1.571,
      "volume_24h": 502398580.04628,
      "rsi_value": 29.509283819628664,
      "rsi_signal": "29.51",
      "bollinger_signal": "Nenhum",
      "macd_signal": "Nenhum",
      "mme_cross": "Nenhum",
      "market_cap": 0.0
    }
  },
  {
    "timestamp": "2025-08-19T11:50:16.223853",
    "symbol": "ETHUSDT",
    "trigger": "FUGA_CAPITAL",
    "data": {
      "symbol": "ETHUSDT",
      "current_price": 4190.42,
      "price_change_24h": -2.37,
      "volume_24h": 2698476001.197399,
      "rsi_value": 28.692398582118983,
      "rsi_signal": "28.69",
      "bollinger_signal": "Nenhum",
      "macd_signal": "Nenhum",
      "mme_cross": "Nenhum",
      "market_cap": 83302
    }
  },
  {
    "timestamp": "2025-08-19T11:50:16.223522",
    "symbol": "ETHUSDT",
    "trigger": "RSI_SOBREVENDA",
    "data": {
      "symbol": "ETHUSDT",
      "current_price": 4190.42,
      "price_change_24h": -2.37,
      "volume_24h": 2698476001.197399,
      "rsi_value": 28.692398582118983,
      "rsi_signal": "28.69",
      "bollinger_signal": "Nenhum",
      "macd_signal": "Nenhum",
      "mme_cross": "Nenhum",
      "market_cap": 83302
    }
  },
  {
    "timestamp": "2025-08-19T11:50:16.223238",
    "symbol": "ETHUSDT",
    "trigger": "PRECO_ACIMA",
    "data": {
      "symbol": "ETHUSDT",
      "current_price": 4190.42,
      "price_change_24h": -2.37,
      "volume_24h": 2698476001.197399,
      "rsi_value": 28.692398582118983,
      "rsi_signal": "28.69",
      "bollinger_signal": "Nenhum",
      "macd_signal": "Nenhum",
      "mme_cross": "Nenhum",
      "market_cap": 83302
    }
  },
  {
    "timestamp": "2025-08-19T11:50:16.020605",
    "symbol": "BTCUSDT",
    "trigger": "CRUZAMENTO_MACD_BAIXA",
    "data": {
      "symbol": "BTCUSDT",
      "current_price": 113784.4,
      "price_change_24h": -1.083,
      "volume_24h": 1532059396.8104985,
      "rsi_value": 23.147493164621594,
      "rsi_signal": "23.15",
      "bollinger_signal": "Abaixo da Banda",
      "macd_signal": "Cruzamento de Baixa",
      "mme_cross": "Nenhum",
      "market_cap": 12975700
    }
  },
  {
    "timestamp": "2025-08-19T11:50:16.020414",
    "symbol": "BTCUSDT",
    "trigger": "PRECO_ABAIXO_BANDA_INFERIOR",
    "data": {
      "symbol": "BTCUSDT",
      "current_price": 113784.4,
      "price_change_24h": -1.083,
      "volume_24h": 1532059396.8104985,
      "rsi_value": 23.147493164621594,
      "rsi_signal": "23.15",
      "bollinger_signal": "Abaixo da Banda",
      "macd_signal": "Cruzamento de Baixa",
      "mme_cross": "Nenhum",
      "market_cap": 12975700
    }
  },
  {
    "timestamp": "2025-08-19T11:50:16.020089",
    "symbol": "BTCUSDT",
    "trigger": "RSI_SOBREVENDA",
    "data": {
      "symbol": "BTCUSDT",
      "current_price": 113784.4,
      "price_change_24h": -1.083,
      "volume_24h": 1532059396.8104985,
      "rsi_value": 23.147493164621594,
      "rsi_signal": "23.15",
      "bollinger_signal": "Abaixo da Banda",
      "macd_signal": "Cruzamento de Baixa",
      "mme_cross": "Nenhum",
      "market_cap": 12975700
    }
  },
  {
    "timestamp": "2025-08-19T11:50:15.803179",
    "symbol": "AAVEUSDT",
    "trigger": "RSI_SOBREVENDA",
    "data": {
      "symbol": "AAVEUSDT",
      "current_price": 279.68,
      "price_change_24h": -2.537,
      "volume_24h": 30936981.82138,
      "rsi_value": 29.87453374025094,
      "rsi_signal": "29.87",
      "bollinger_signal": "Nenhum",
      "macd_signal": "Nenhum",
      "mme_cross": "Nenhum",
      "market_cap": 4265534183
    }
  },
  {
    "timestamp": "2025-08-19T11:45:03.222548",
    "symbol": "SOLVUSDT",
    "trigger": "CRUZAMENTO_MACD_BAIXA",
    "data": {
      "symbol": "SOLVUSDT",
      "current_price": 0.04328,
      "price_change_24h": -2.501,
      "volume_24h": 1278078.85195,
      "rsi_value": 33.33333333333333,
      "rsi_signal": "33.33",
      "bollinger_signal": "Abaixo da Banda",
      "macd_signal": "Cruzamento de Baixa",
      "mme_cross": "Nenhum",
      "market_cap": 64069935
    }
  },
  {
    "timestamp": "2025-08-19T11:45:03.222245",
    "symbol": "SOLVUSDT",
    "trigger": "PRECO_ABAIXO_BANDA_INFERIOR",
    "data": {
      "symbol": "SOLVUSDT",
      "current_price": 0.04328,
      "price_change_24h": -2.501,
      "volume_24h": 1278078.85195,
      "rsi_value": 33.33333333333333,
      "rsi_signal": "33.33",
      "bollinger_signal": "Abaixo da Banda",
      "macd_signal": "Cruzamento de Baixa",
      "mme_cross": "Nenhum",
      "market_cap": 64069935
    }
  },
  {
    "timestamp": "2025-08-19T11:45:02.817866",
    "symbol": "SOLUSDT",
    "trigger": "RSI_SOBREVENDA",
    "data": {
      "symbol": "SOLUSDT",
      "current_price": 178.74,
      "price_change_24h": -1.559,
      "volume_24h": 500868928.38323,
      "rsi_value": 29.31488801054016,
      "rsi_signal": "29.31",
      "bollinger_signal": "Nenhum",
      "macd_signal": "Nenhum",
      "mme_cross": "Nenhum",
      "market_cap": 0.0
    }
  },
  {
    "timestamp": "2025-08-19T11:45:02.073513",
    "symbol": "ETHUSDT",
    "trigger": "FUGA_CAPITAL",
    "data": {
      "symbol": "ETHUSDT",
      "current_price": 4201.89,
      "price_change_24h": -2.214,
      "volume_24h": 2650838174.745793,
      "rsi_value": 29.59148145998961,
      "rsi_signal": "29.59",
      "bollinger_signal": "Nenhum",
      "macd_signal": "Nenhum",
      "mme_cross": "Nenhum",
      "market_cap": 83302
    }
  },
  {
    "timestamp": "2025-08-19T11:45:02.073205",
    "symbol": "ETHUSDT",
    "trigger": "PRECO_ACIMA",
    "data": {
      "symbol": "ETHUSDT",
      "current_price": 4201.89,
      "price_change_24h": -2.214,
      "volume_24h": 2650838174.745793,
      "rsi_value": 29.59148145998961,
      "rsi_signal": "29.59",
      "bollinger_signal": "Nenhum",
      "macd_signal": "Nenhum",
      "mme_cross": "Nenhum",
      "market_cap": 83302
    }
  },
  {
    "timestamp": "2025-08-19T11:45:01.255311",
    "symbol": "BTCUSDT",
    "trigger": "CRUZAMENTO_MACD_BAIXA",
    "data": {
      "symbol": "BTCUSDT",
      "current_price": 113925.66,
      "price_change_24h": -1.062,
      "volume_24h": 1494606526.6582594,
      "rsi_value": 23.443858145067054,
      "rsi_signal": "23.44",
      "bollinger_signal": "Abaixo da Banda",
      "macd_signal": "Cruzamento de Baixa",
      "mme_cross": "Nenhum",
      "market_cap": 12975700
    }
  },
  {
    "timestamp": "2025-08-19T11:45:01.254949",
    "symbol": "BTCUSDT",
    "trigger": "PRECO_ABAIXO_BANDA_INFERIOR",
    "data": {
      "symbol": "BTCUSDT",
      "current_price": 113925.66,
      "price_change_24h": -1.062,
      "volume_24h": 1494606526.6582594,
      "rsi_value": 23.443858145067054,
      "rsi_signal": "23.44",
      "bollinger_signal": "Abaixo da Banda",
      "macd_signal": "Cruzamento de Baixa",
      "mme_cross": "Nenhum",
      "market_cap": 12975700
    }
  },
  {
    "timestamp": "2025-08-19T11:45:00.639934",
    "symbol": "BNBUSDT",
    "trigger": "PRECO_ABAIXO_BANDA_INFERIOR",
    "data": {
      "symbol": "BNBUSDT",
      "current_price": 831.98,
      "price_change_24h": -0.559,
      "volume_24h": 152252531.07579,
      "rsi_value": 36.380832282471715,
      "rsi_signal": "36.38",
      "bollinger_signal": "Abaixo da Banda",
      "macd_signal": "Nenhum",
      "mme_cross": "Nenhum",
      "market_cap": 0.0
    }
  },
  {
    "timestamp": "2025-08-19T10:49:34.870597",
    "symbol": "ETHUSDT",
    "trigger": "PRECO_ACIMA",
    "data": {
      "symbol": "ETHUSDT",
      "current_price": 4270.51,
      "price_change_24h": -1.198,
      "volume_24h": 2525445085.608885,
      "rsi_value": 43.03747663857846,
      "rsi_signal": "43.04",
      "bollinger_signal": "Nenhum",
      "macd_signal": "Nenhum",
      "mme_cross": "Nenhum",
      "market_cap": 83957
    }
  },
  {
    "timestamp": "2025-08-19T10:49:33.654887",
    "symbol": "BNBUSDT",
    "trigger": "CRUZAMENTO_MACD_BAIXA",
    "data": {
      "symbol": "BNBUSDT",
      "current_price": 841.05,
      "price_change_24h": 0.567,
      "volume_24h": 142832920.68214,
      "rsi_value": 44.7112837718524,
      "rsi_signal": "44.71",
      "bollinger_signal": "Nenhum",
      "macd_signal": "Cruzamento de Baixa",
      "mme_cross": "Nenhum",
      "market_cap": 0.0
    }
  },
  {
    "timestamp": "2025-08-19T07:51:49.348287",
    "symbol": "ETHUSDT",
    "trigger": "CRUZAMENTO_MACD_ALTA",
    "data": {
      "symbol": "ETHUSDT",
      "current_price": 4280.23,
      "price_change_24h": -0.018,
      "volume_24h": 2683002202.373437,
      "rsi_value": 41.3409310540173,
      "rsi_signal": "41.34",
      "bollinger_signal": "Nenhum",
      "macd_signal": "Cruzamento de Alta",
      "mme_cross": "Nenhum",
      "market_cap": 84249
    }
  },
  {
    "timestamp": "2025-08-19T07:51:49.347962",
    "symbol": "ETHUSDT",
    "trigger": "PRECO_ACIMA",
    "data": {
      "symbol": "ETHUSDT",
      "current_price": 4280.23,
      "price_change_24h": -0.018,
      "volume_24h": 2683002202.373437,
      "rsi_value": 41.3409310540173,
      "rsi_signal": "41.34",
      "bollinger_signal": "Nenhum",
      "macd_signal": "Cruzamento de Alta",
      "mme_cross": "Nenhum",
      "market_cap": 84249
    }
  },
  {
    "timestamp": "2025-08-19T07:38:06.806628",
    "symbol": "ETHUSDT",
    "trigger": "CRUZAMENTO_MACD_ALTA",
    "data": {
      "symbol": "ETHUSDT",
      "current_price": 4294.5,
      "price_change_24h": 0.278,
      "volume_24h": 2683242470.075038,
      "rsi_value": 42.302380639221475,
      "rsi_signal": "42.30",
      "bollinger_signal": "Nenhum",
      "macd_signal": "Cruzamento de Alta",
      "mme_cross": "Nenhum",
      "market_cap": 84215
    }
  },
  {
    "timestamp": "2025-08-19T07:38:06.806282",
    "symbol": "ETHUSDT",
    "trigger": "PRECO_ACIMA",
    "data": {
      "symbol": "ETHUSDT",
      "current_price": 4294.5,
      "price_change_24h": 0.278,
      "volume_24h": 2683242470.075038,
      "rsi_value": 42.302380639221475,
      "rsi_signal": "42.30",
      "bollinger_signal": "Nenhum",
      "macd_signal": "Cruzamento de Alta",
      "mme_cross": "Nenhum",
      "market_cap": 84215
    }
  },
  {
    "timestamp": "2025-08-19T07:33:03.618211",
    "symbol": "ETHUSDT",
    "trigger": "CRUZAMENTO_MACD_ALTA",
    "data": {
      "symbol": "ETHUSDT",
      "current_price": 4286.2,
      "price_change_24h": 0.137,
      "volume_24h": 2685432867.867333,
      "rsi_value": 42.298585991450395,
      "rsi_signal": "42.30",
      "bollinger_signal": "Nenhum",
      "macd_signal": "Cruzamento de Alta",
      "mme_cross": "Nenhum",
      "market_cap": 84215
    }
  },
  {
    "timestamp": "2025-08-19T07:33:03.617875",
    "symbol": "ETHUSDT",
    "trigger": "PRECO_ACIMA",
    "data": {
      "symbol": "ETHUSDT",
      "current_price": 4286.2,
      "price_change_24h": 0.137,
      "volume_24h": 2685432867.867333,
      "rsi_value": 42.298585991450395,
      "rsi_signal": "42.30",
      "bollinger_signal": "Nenhum",
      "macd_signal": "Cruzamento de Alta",
      "mme_cross": "Nenhum",
      "market_cap": 84215
    }
  },
  {
    "timestamp": "2025-08-19T07:20:41.817089",
    "symbol": "ETHUSDT",
    "trigger": "CRUZAMENTO_MACD_ALTA",
    "data": {
      "symbol": "ETHUSDT",
      "current_price": 4287.9,
      "price_change_24h": -0.222,
      "volume_24h": 2696182727.748089,
      "rsi_value": 42.77654578659033,
      "rsi_signal": "42.78",
      "bollinger_signal": "Nenhum",
      "macd_signal": "Cruzamento de Alta",
      "mme_cross": "Nenhum",
      "market_cap": 84147
    }
  },
  {
    "timestamp": "2025-08-19T07:20:41.816808",
    "symbol": "ETHUSDT",
    "trigger": "PRECO_ACIMA",
    "data": {
      "symbol": "ETHUSDT",
      "current_price": 4287.9,
      "price_change_24h": -0.222,
      "volume_24h": 2696182727.748089,
      "rsi_value": 42.77654578659033,
      "rsi_signal": "42.78",
      "bollinger_signal": "Nenhum",
      "macd_signal": "Cruzamento de Alta",
      "mme_cross": "Nenhum",
      "market_cap": 84147
    }
  },
  {
    "timestamp": "2025-08-19T07:15:38.448340",
    "symbol": "ETHUSDT",
    "trigger": "CRUZAMENTO_MACD_ALTA",
    "data": {
      "symbol": "ETHUSDT",
      "current_price": 4282.79,
      "price_change_24h": -0.098,
      "volume_24h": 2699041964.223534,
      "rsi_value": 41.8067853944882,
      "rsi_signal": "41.81",
      "bollinger_signal": "Nenhum",
      "macd_signal": "Cruzamento de Alta",
      "mme_cross": "Nenhum",
      "market_cap": 83723
    }
  },
  {
    "timestamp": "2025-08-19T07:15:38.448022",
    "symbol": "ETHUSDT",
    "trigger": "PRECO_ACIMA",
    "data": {
      "symbol": "ETHUSDT",
      "current_price": 4282.79,
      "price_change_24h": -0.098,
      "volume_24h": 2699041964.223534,
      "rsi_value": 41.8067853944882,
      "rsi_signal": "41.81",
      "bollinger_signal": "Nenhum",
      "macd_signal": "Cruzamento de Alta",
      "mme_cross": "Nenhum",
      "market_cap": 83723
    }
  },
  {
    "timestamp": "2025-08-19T06:56:39.497748",
    "symbol": "SOLUSDT",
    "trigger": "CRUZAMENTO_MACD_ALTA",
    "data": {
      "symbol": "SOLUSDT",
      "current_price": 181.43,
      "price_change_24h": 0.055,
      "volume_24h": 503579823.01597,
      "rsi_value": 43.87405886379184,
      "rsi_signal": "43.87",
      "bollinger_signal": "Nenhum",
      "macd_signal": "Cruzamento de Alta",
      "mme_cross": "Nenhum",
      "market_cap": 0.0
    }
  },
  {
    "timestamp": "2025-08-19T06:56:38.887223",
    "symbol": "ETHUSDT",
    "trigger": "PRECO_ACIMA",
    "data": {
      "symbol": "ETHUSDT",
      "current_price": 4278.64,
      "price_change_24h": -0.501,
      "volume_24h": 2725457157.534067,
      "rsi_value": 38.09449506927983,
      "rsi_signal": "38.09",
      "bollinger_signal": "Nenhum",
      "macd_signal": "Nenhum",
      "mme_cross": "Nenhum",
      "market_cap": 84225
    }
  },
  {
    "timestamp": "2025-08-19T06:52:28.873252",
    "symbol": "SOLUSDT",
    "trigger": "CRUZAMENTO_MACD_ALTA",
    "data": {
      "symbol": "SOLUSDT",
      "current_price": 181.24,
      "price_change_24h": -0.176,
      "volume_24h": 503957368.86596,
      "rsi_value": 43.17394317394317,
      "rsi_signal": "43.17",
      "bollinger_signal": "Nenhum",
      "macd_signal": "Cruzamento de Alta",
      "mme_cross": "Nenhum",
      "market_cap": 0.0
    }
  },
  {
    "timestamp": "2025-08-19T06:52:28.262767",
    "symbol": "ETHUSDT",
    "trigger": "PRECO_ACIMA",
    "data": {
      "symbol": "ETHUSDT",
      "current_price": 4279.19,
      "price_change_24h": -0.761,
      "volume_24h": 2733955751.268095,
      "rsi_value": 38.17167435481862,
      "rsi_signal": "38.17",
      "bollinger_signal": "Nenhum",
      "macd_signal": "Nenhum",
      "mme_cross": "Nenhum",
      "market_cap": 84225
    }
  },
  {
    "timestamp": "2025-08-19T06:47:24.634154",
    "symbol": "SOLUSDT",
    "trigger": "CRUZAMENTO_MACD_ALTA",
    "data": {
      "symbol": "SOLUSDT",
      "current_price": 181.43,
      "price_change_24h": -0.083,
      "volume_24h": 505295129.40647,
      "rsi_value": 43.87405886379184,
      "rsi_signal": "43.87",
      "bollinger_signal": "Nenhum",
      "macd_signal": "Cruzamento de Alta",
      "mme_cross": "Nenhum",
      "market_cap": 0.0
    }
  },
  {
    "timestamp": "2025-08-19T06:47:24.217369",
    "symbol": "ETHUSDT",
    "trigger": "PRECO_ACIMA",
    "data": {
      "symbol": "ETHUSDT",
      "current_price": 4280.0,
      "price_change_24h": -0.733,
      "volume_24h": 2740284588.154254,
      "rsi_value": 38.325457032707426,
      "rsi_signal": "38.33",
      "bollinger_signal": "Nenhum",
      "macd_signal": "Nenhum",
      "mme_cross": "Nenhum",
      "market_cap": 83977
    }
  },
  {
    "timestamp": "2025-08-19T06:29:53.978258",
    "symbol": "SOLUSDT",
    "trigger": "CRUZAMENTO_MACD_ALTA",
    "data": {
      "symbol": "SOLUSDT",
      "current_price": 181.92,
      "price_change_24h": 0.854,
      "volume_24h": 507828684.64127,
      "rsi_value": 45.65937707090787,
      "rsi_signal": "45.66",
      "bollinger_signal": "Nenhum",
      "macd_signal": "Cruzamento de Alta",
      "mme_cross": "Nenhum",
      "market_cap": 0.0
    }
  },
  {
    "timestamp": "2025-08-19T06:29:53.558880",
    "symbol": "ETHUSDT",
    "trigger": "ENTRADA_CAPITAL",
    "data": {
      "symbol": "ETHUSDT",
      "current_price": 4280.6,
      "price_change_24h": 1.05,
      "volume_24h": 2820565971.147925,
      "rsi_value": 38.367613247996125,
      "rsi_signal": "38.37",
      "bollinger_signal": "Nenhum",
      "macd_signal": "Nenhum",
      "mme_cross": "Nenhum",
      "market_cap": 84015
    }
  },
  {
    "timestamp": "2025-08-19T06:29:53.558537",
    "symbol": "ETHUSDT",
    "trigger": "PRECO_ACIMA",
    "data": {
      "symbol": "ETHUSDT",
      "current_price": 4280.6,
      "price_change_24h": 1.05,
      "volume_24h": 2820565971.147925,
      "rsi_value": 38.367613247996125,
      "rsi_signal": "38.37",
      "bollinger_signal": "Nenhum",
      "macd_signal": "Nenhum",
      "mme_cross": "Nenhum",
      "market_cap": 84015
    }
  },
  {
    "timestamp": "2025-08-19T05:00:42.341846",
    "symbol": "ETHUSDT",
    "trigger": "Pre\u00e7o Acima de $3500.00 (Atual: $4236.73)",
    "data": {
      "symbol": "ETHUSDT",
      "current_price": 4236.73,
      "price_change_24h": -0.611,
      "volume_24h": 2856393137.584663,
      "rsi_value": 27.41946633485442,
      "rsi_signal": "27.42",
      "bollinger_signal": "Nenhum",
      "macd_signal": "Nenhum",
      "mme_cross": "Nenhum",
      "market_cap": 83188
    }
  },
  {
    "timestamp": "2025-08-19T04:52:32.914814",
    "symbol": "ETHUSDT",
    "trigger": "Pre\u00e7o Acima de $3500.00 (Atual: $4232.80)",
    "data": {
      "symbol": "ETHUSDT",
      "current_price": 4232.8,
      "price_change_24h": -0.507,
      "volume_24h": 2866550868.649726,
      "rsi_value": 32.24407817132666,
      "rsi_signal": "32.24",
      "bollinger_signal": "Nenhum",
      "macd_signal": "Nenhum",
      "mme_cross": "Nenhum",
      "market_cap": 83176
    }
  },
  {
    "timestamp": "2025-08-18T01:17:44.103561",
    "symbol": "SOLUSDT",
    "trigger": "Pre\u00e7o Abaixo da Banda Inferior de Bollinger",
    "data": {
      "symbol": "SOLUSDT",
      "current_price": 182.47,
      "price_change_24h": -5.146,
      "volume_24h": 560374666.59939,
      "rsi_value": 20.200951877313557,
      "rsi_signal": "20.20",
      "bollinger_signal": "Abaixo da Banda",
      "macd_signal": "Nenhum",
      "mme_cross": "Nenhum",
      "market_cap": 0.0
    }
  },
  {
    "timestamp": "2025-08-18T01:17:44.103110",
    "symbol": "SOLUSDT",
    "trigger": "RSI Sobrevendido (RSI <= 30.00 | Atual: 20.20)",
    "data": {
      "symbol": "SOLUSDT",
      "current_price": 182.47,
      "price_change_24h": -5.146,
      "volume_24h": 560374666.59939,
      "rsi_value": 20.200951877313557,
      "rsi_signal": "20.20",
      "bollinger_signal": "Abaixo da Banda",
      "macd_signal": "Nenhum",
      "mme_cross": "Nenhum",
      "market_cap": 0.0
    }
  },
  {
    "timestamp": "2025-08-18T01:17:43.497758",
    "symbol": "ETHUSDT",
    "trigger": "Pre\u00e7o Acima de $3500.00 (Atual: $4322.71)",
    "data": {
      "symbol": "ETHUSDT",
      "current_price": 4322.71,
      "price_change_24h": -3.083,
      "volume_24h": 2838693386.01236,
      "rsi_value": 20.41266745367743,
      "rsi_signal": "20.41",
      "bollinger_signal": "Nenhum",
      "macd_signal": "Nenhum",
      "mme_cross": "Nenhum",
      "market_cap": 84668
    }
  },
  {
    "timestamp": "2025-08-18T01:17:43.497357",
    "symbol": "ETHUSDT",
    "trigger": "Fuga de Capital (Vol > 1.00% Cap.Merc. e Var < -2.00%)",
    "data": {
      "symbol": "ETHUSDT",
      "current_price": 4322.71,
      "price_change_24h": -3.083,
      "volume_24h": 2838693386.01236,
      "rsi_value": 20.41266745367743,
      "rsi_signal": "20.41",
      "bollinger_signal": "Nenhum",
      "macd_signal": "Nenhum",
      "mme_cross": "Nenhum",
      "market_cap": 84668
    }
  },
  {
    "timestamp": "2025-08-18T01:17:42.892420",
    "symbol": "BTCUSDT",
    "trigger": "Pre\u00e7o Abaixo da Banda Inferior de Bollinger",
    "data": {
      "symbol": "BTCUSDT",
      "current_price": 115361.13,
      "price_change_24h": -1.997,
      "volume_24h": 1299717267.9628024,
      "rsi_value": 15.384481597706497,
      "rsi_signal": "15.38",
      "bollinger_signal": "Abaixo da Banda",
      "macd_signal": "Nenhum",
      "mme_cross": "Nenhum",
      "market_cap": 13044675
    }
  },
  {
    "timestamp": "2025-08-18T01:17:42.477906",
    "symbol": "BNBUSDT",
    "trigger": "Pre\u00e7o Abaixo da Banda Inferior de Bollinger",
    "data": {
      "symbol": "BNBUSDT",
      "current_price": 835.35,
      "price_change_24h": -1.402,
      "volume_24h": 166383367.65913,
      "rsi_value": 23.972445464982727,
      "rsi_signal": "23.97",
      "bollinger_signal": "Abaixo da Banda",
      "macd_signal": "Nenhum",
      "mme_cross": "Nenhum",
      "market_cap": 0.0
    }
  },
  {
    "timestamp": "2025-08-18T01:17:42.477564",
    "symbol": "BNBUSDT",
    "trigger": "RSI Sobrevendido (RSI <= 30.00 | Atual: 23.97)",
    "data": {
      "symbol": "BNBUSDT",
      "current_price": 835.35,
      "price_change_24h": -1.402,
      "volume_24h": 166383367.65913,
      "rsi_value": 23.972445464982727,
      "rsi_signal": "23.97",
      "bollinger_signal": "Abaixo da Banda",
      "macd_signal": "Nenhum",
      "mme_cross": "Nenhum",
      "market_cap": 0.0
    }
  },
  {
    "timestamp": "2025-08-18T00:34:21.847550",
    "symbol": "SOLUSDT",
    "trigger": "Pre\u00e7o Abaixo da Banda Inferior de Bollinger",
    "data": {
      "symbol": "SOLUSDT",
      "current_price": 182.68,
      "price_change_24h": -4.441,
      "volume_24h": 544768925.08212,
      "rsi_value": 22.689511941848394,
      "rsi_signal": "22.69",
      "bollinger_signal": "Abaixo da Banda",
      "macd_signal": "Nenhum",
      "mme_cross": "Nenhum",
      "market_cap": 0.0
    }
  },
  {
    "timestamp": "2025-08-18T00:34:21.846945",
    "symbol": "SOLUSDT",
    "trigger": "RSI Sobrevendido (RSI <= 30.00 | Atual: 22.69)",
    "data": {
      "symbol": "SOLUSDT",
      "current_price": 182.68,
      "price_change_24h": -4.441,
      "volume_24h": 544768925.08212,
      "rsi_value": 22.689511941848394,
      "rsi_signal": "22.69",
      "bollinger_signal": "Abaixo da Banda",
      "macd_signal": "Nenhum",
      "mme_cross": "Nenhum",
      "market_cap": 0.0
    }
  },
  {
    "timestamp": "2025-08-18T00:34:21.242692",
    "symbol": "ETHUSDT",
    "trigger": "Pre\u00e7o Abaixo da Banda Inferior de Bollinger",
    "data": {
      "symbol": "ETHUSDT",
      "current_price": 4295.59,
      "price_change_24h": -3.162,
      "volume_24h": 2785538182.742946,
      "rsi_value": 21.8802189645573,
      "rsi_signal": "21.88",
      "bollinger_signal": "Abaixo da Banda",
      "macd_signal": "Nenhum",
      "mme_cross": "Nenhum",
      "market_cap": 85982
    }
  },
  {
    "timestamp": "2025-08-18T00:34:21.242502",
    "symbol": "ETHUSDT",
    "trigger": "Pre\u00e7o Acima de $3500.00 (Atual: $4295.59)",
    "data": {
      "symbol": "ETHUSDT",
      "current_price": 4295.59,
      "price_change_24h": -3.162,
      "volume_24h": 2785538182.742946,
      "rsi_value": 21.8802189645573,
      "rsi_signal": "21.88",
      "bollinger_signal": "Abaixo da Banda",
      "macd_signal": "Nenhum",
      "mme_cross": "Nenhum",
      "market_cap": 85982
    }
  },
  {
    "timestamp": "2025-08-18T00:34:21.242008",
    "symbol": "ETHUSDT",
    "trigger": "Fuga de Capital (Vol > 1.00% Cap.Merc. e Var < -2.00%)",
    "data": {
      "symbol": "ETHUSDT",
      "current_price": 4295.59,
      "price_change_24h": -3.162,
      "volume_24h": 2785538182.742946,
      "rsi_value": 21.8802189645573,
      "rsi_signal": "21.88",
      "bollinger_signal": "Abaixo da Banda",
      "macd_signal": "Nenhum",
      "mme_cross": "Nenhum",
      "market_cap": 85982
    }
  },
  {
    "timestamp": "2025-08-18T00:34:20.638105",
    "symbol": "BTCUSDT",
    "trigger": "Pre\u00e7o Abaixo da Banda Inferior de Bollinger",
    "data": {
      "symbol": "BTCUSDT",
      "current_price": 115212.18,
      "price_change_24h": -2.02,
      "volume_24h": 1222437364.1595745,
      "rsi_value": 13.146761302663919,
      "rsi_signal": "13.15",
      "bollinger_signal": "Abaixo da Banda",
      "macd_signal": "Nenhum",
      "mme_cross": "Nenhum",
      "market_cap": 13054122
    }
  },
  {
    "timestamp": "2025-08-18T00:34:20.233845",
    "symbol": "BNBUSDT",
    "trigger": "Pre\u00e7o Abaixo da Banda Inferior de Bollinger",
    "data": {
      "symbol": "BNBUSDT",
      "current_price": 833.16,
      "price_change_24h": -1.245,
      "volume_24h": 164062789.06244,
      "rsi_value": 23.149571710959606,
      "rsi_signal": "23.15",
      "bollinger_signal": "Abaixo da Banda",
      "macd_signal": "Nenhum",
      "mme_cross": "Nenhum",
      "market_cap": 0.0
    }
  },
  {
    "timestamp": "2025-08-18T00:34:20.233461",
    "symbol": "BNBUSDT",
    "trigger": "RSI Sobrevendido (RSI <= 30.00 | Atual: 23.15)",
    "data": {
      "symbol": "BNBUSDT",
      "current_price": 833.16,
      "price_change_24h": -1.245,
      "volume_24h": 164062789.06244,
      "rsi_value": 23.149571710959606,
      "rsi_signal": "23.15",
      "bollinger_signal": "Abaixo da Banda",
      "macd_signal": "Nenhum",
      "mme_cross": "Nenhum",
      "market_cap": 0.0
    }
  },
  {
    "timestamp": "2025-08-18T00:29:18.766654",
    "symbol": "SOLUSDT",
    "trigger": "Pre\u00e7o Abaixo da Banda Inferior de Bollinger",
    "data": {
      "symbol": "SOLUSDT",
      "current_price": 183.77,
      "price_change_24h": -3.619,
      "volume_24h": 537941990.98884,
      "rsi_value": 24.0506329113924,
      "rsi_signal": "24.05",
      "bollinger_signal": "Abaixo da Banda",
      "macd_signal": "Nenhum",
      "mme_cross": "Nenhum",
      "market_cap": 0.0
    }
  },
  {
    "timestamp": "2025-08-18T00:29:18.766365",
    "symbol": "SOLUSDT",
    "trigger": "RSI Sobrevendido (RSI <= 30.00 | Atual: 24.05)",
    "data": {
      "symbol": "SOLUSDT",
      "current_price": 183.77,
      "price_change_24h": -3.619,
      "volume_24h": 537941990.98884,
      "rsi_value": 24.0506329113924,
      "rsi_signal": "24.05",
      "bollinger_signal": "Abaixo da Banda",
      "macd_signal": "Nenhum",
      "mme_cross": "Nenhum",
      "market_cap": 0.0
    }
  },
  {
    "timestamp": "2025-08-18T00:29:18.351509",
    "symbol": "ETHUSDT",
    "trigger": "Pre\u00e7o Abaixo da Banda Inferior de Bollinger",
    "data": {
      "symbol": "ETHUSDT",
      "current_price": 4307.57,
      "price_change_24h": -2.84,
      "volume_24h": 2719359718.081389,
      "rsi_value": 22.66295077240933,
      "rsi_signal": "22.66",
      "bollinger_signal": "Abaixo da Banda",
      "macd_signal": "Nenhum",
      "mme_cross": "Nenhum",
      "market_cap": 85982
    }
  },
  {
    "timestamp": "2025-08-18T00:29:18.351329",
    "symbol": "ETHUSDT",
    "trigger": "Pre\u00e7o Acima de $3500.00 (Atual: $4307.57)",
    "data": {
      "symbol": "ETHUSDT",
      "current_price": 4307.57,
      "price_change_24h": -2.84,
      "volume_24h": 2719359718.081389,
      "rsi_value": 22.66295077240933,
      "rsi_signal": "22.66",
      "bollinger_signal": "Abaixo da Banda",
      "macd_signal": "Nenhum",
      "mme_cross": "Nenhum",
      "market_cap": 85982
    }
  },
  {
    "timestamp": "2025-08-18T00:29:18.350870",
    "symbol": "ETHUSDT",
    "trigger": "Fuga de Capital (Vol > 1.00% Cap.Merc. e Var < -2.00%)",
    "data": {
      "symbol": "ETHUSDT",
      "current_price": 4307.57,
      "price_change_24h": -2.84,
      "volume_24h": 2719359718.081389,
      "rsi_value": 22.66295077240933,
      "rsi_signal": "22.66",
      "bollinger_signal": "Abaixo da Banda",
      "macd_signal": "Nenhum",
      "mme_cross": "Nenhum",
      "market_cap": 85982
    }
  },
  {
    "timestamp": "2025-08-18T00:29:17.748285",
    "symbol": "BTCUSDT",
    "trigger": "Pre\u00e7o Abaixo da Banda Inferior de Bollinger",
    "data": {
      "symbol": "BTCUSDT",
      "current_price": 115346.12,
      "price_change_24h": -1.895,
      "volume_24h": 1200625882.402005,
      "rsi_value": 13.573524339597142,
      "rsi_signal": "13.57",
      "bollinger_signal": "Abaixo da Banda",
      "macd_signal": "Nenhum",
      "mme_cross": "Nenhum",
      "market_cap": 13056241
    }
  },
  {
    "timestamp": "2025-08-18T00:29:17.344692",
    "symbol": "BNBUSDT",
    "trigger": "Pre\u00e7o Abaixo da Banda Inferior de Bollinger",
    "data": {
      "symbol": "BNBUSDT",
      "current_price": 833.21,
      "price_change_24h": -1.339,
      "volume_24h": 162867666.26763,
      "rsi_value": 23.00305543430798,
      "rsi_signal": "23.00",
      "bollinger_signal": "Abaixo da Banda",
      "macd_signal": "Nenhum",
      "mme_cross": "Nenhum",
      "market_cap": 0.0
    }
  },
  {
    "timestamp": "2025-08-18T00:29:17.344225",
    "symbol": "BNBUSDT",
    "trigger": "RSI Sobrevendido (RSI <= 30.00 | Atual: 23.00)",
    "data": {
      "symbol": "BNBUSDT",
      "current_price": 833.21,
      "price_change_24h": -1.339,
      "volume_24h": 162867666.26763,
      "rsi_value": 23.00305543430798,
      "rsi_signal": "23.00",
      "bollinger_signal": "Abaixo da Banda",
      "macd_signal": "Nenhum",
      "mme_cross": "Nenhum",
      "market_cap": 0.0
    }
  },
  {
    "timestamp": "2025-08-18T00:24:15.831185",
    "symbol": "SOLUSDT",
    "trigger": "Pre\u00e7o Abaixo da Banda Inferior de Bollinger",
    "data": {
      "symbol": "SOLUSDT",
      "current_price": 184.07,
      "price_change_24h": -3.385,
      "volume_24h": 537595311.95731,
      "rsi_value": 25.01374381528315,
      "rsi_signal": "25.01",
      "bollinger_signal": "Abaixo da Banda",
      "macd_signal": "Nenhum",
      "mme_cross": "Nenhum",
      "market_cap": 0.0
    }
  },
  {
    "timestamp": "2025-08-18T00:24:15.830671",
    "symbol": "SOLUSDT",
    "trigger": "RSI Sobrevendido (RSI <= 30.00 | Atual: 25.01)",
    "data": {
      "symbol": "SOLUSDT",
      "current_price": 184.07,
      "price_change_24h": -3.385,
      "volume_24h": 537595311.95731,
      "rsi_value": 25.01374381528315,
      "rsi_signal": "25.01",
      "bollinger_signal": "Abaixo da Banda",
      "macd_signal": "Nenhum",
      "mme_cross": "Nenhum",
      "market_cap": 0.0
    }
  },
  {
    "timestamp": "2025-08-18T00:24:15.213212",
    "symbol": "ETHUSDT",
    "trigger": "Pre\u00e7o Abaixo da Banda Inferior de Bollinger",
    "data": {
      "symbol": "ETHUSDT",
      "current_price": 4318.98,
      "price_change_24h": -2.626,
      "volume_24h": 2709332351.105397,
      "rsi_value": 23.26091781125922,
      "rsi_signal": "23.26",
      "bollinger_signal": "Abaixo da Banda",
      "macd_signal": "Nenhum",
      "mme_cross": "Nenhum",
      "market_cap": 85629
    }
  },
  {
    "timestamp": "2025-08-18T00:24:15.212921",
    "symbol": "ETHUSDT",
    "trigger": "Pre\u00e7o Acima de $3500.00 (Atual: $4318.98)",
    "data": {
      "symbol": "ETHUSDT",
      "current_price": 4318.98,
      "price_change_24h": -2.626,
      "volume_24h": 2709332351.105397,
      "rsi_value": 23.26091781125922,
      "rsi_signal": "23.26",
      "bollinger_signal": "Abaixo da Banda",
      "macd_signal": "Nenhum",
      "mme_cross": "Nenhum",
      "market_cap": 85629
    }
  },
  {
    "timestamp": "2025-08-18T00:24:15.212527",
    "symbol": "ETHUSDT",
    "trigger": "Fuga de Capital (Vol > 1.00% Cap.Merc. e Var < -2.00%)",
    "data": {
      "symbol": "ETHUSDT",
      "current_price": 4318.98,
      "price_change_24h": -2.626,
      "volume_24h": 2709332351.105397,
      "rsi_value": 23.26091781125922,
      "rsi_signal": "23.26",
      "bollinger_signal": "Abaixo da Banda",
      "macd_signal": "Nenhum",
      "mme_cross": "Nenhum",
      "market_cap": 85629
    }
  },
  {
    "timestamp": "2025-08-18T00:24:14.403077",
    "symbol": "BTCUSDT",
    "trigger": "Pre\u00e7o Abaixo da Banda Inferior de Bollinger",
    "data": {
      "symbol": "BTCUSDT",
      "current_price": 115396.93,
      "price_change_24h": -1.827,
      "volume_24h": 1197240109.52209,
      "rsi_value": 13.738463009899434,
      "rsi_signal": "13.74",
      "bollinger_signal": "Abaixo da Banda",
      "macd_signal": "Nenhum",
      "mme_cross": "Nenhum",
      "market_cap": 13069932
    }
  },
  {
    "timestamp": "2025-08-18T00:24:13.788495",
    "symbol": "BNBUSDT",
    "trigger": "Pre\u00e7o Abaixo da Banda Inferior de Bollinger",
    "data": {
      "symbol": "BNBUSDT",
      "current_price": 835.72,
      "price_change_24h": -1.048,
      "volume_24h": 161934248.9263,
      "rsi_value": 24.353049907578352,
      "rsi_signal": "24.35",
      "bollinger_signal": "Abaixo da Banda",
      "macd_signal": "Nenhum",
      "mme_cross": "Nenhum",
      "market_cap": 0.0
    }
  },
  {
    "timestamp": "2025-08-18T00:24:13.787703",
    "symbol": "BNBUSDT",
    "trigger": "RSI Sobrevendido (RSI <= 30.00 | Atual: 24.35)",
    "data": {
      "symbol": "BNBUSDT",
      "current_price": 835.72,
      "price_change_24h": -1.048,
      "volume_24h": 161934248.9263,
      "rsi_value": 24.353049907578352,
      "rsi_signal": "24.35",
      "bollinger_signal": "Abaixo da Banda",
      "macd_signal": "Nenhum",
      "mme_cross": "Nenhum",
      "market_cap": 0.0
    }
  },
  {
    "timestamp": "2025-08-16T18:49:26.417270",
    "symbol": "ETHUSDT",
    "trigger": "Pre\u00e7o Acima de $3500.00 (Atual: $4421.73)",
    "data": {
      "symbol": "ETHUSDT",
      "current_price": 4421.73,
      "price_change_24h": 0.126,
      "volume_24h": 1894598097.469084,
      "rsi_value": 42.33957629720609,
      "rsi_signal": "42.34",
      "bollinger_signal": "Nenhum",
      "macd_signal": "Nenhum",
      "mme_cross": "Nenhum",
      "market_cap": 86145
    }
  },
  {
    "timestamp": "2025-08-16T17:56:23.018773",
    "symbol": "ETHUSDT",
    "trigger": "Pre\u00e7o Acima de $3500.00 (Atual: $4426.44)",
    "data": {
      "symbol": "ETHUSDT",
      "current_price": 4426.44,
      "price_change_24h": 0.25,
      "volume_24h": 2028678858.072288,
      "rsi_value": 51.711508663191985,
      "rsi_signal": "51.71",
      "bollinger_signal": "Nenhum",
      "macd_signal": "Nenhum",
      "mme_cross": "Nenhum",
      "market_cap": 85583
    }
  },
  {
    "timestamp": "2025-08-16T16:03:23.125836",
    "symbol": "ETHUSDT",
    "trigger": "Pre\u00e7o Acima de $3500.00 (Atual: $4410.63)",
    "data": {
      "symbol": "ETHUSDT",
      "current_price": 4410.63,
      "price_change_24h": 0.535,
      "volume_24h": 2142260755.038401,
      "rsi_value": 47.385571765177666,
      "rsi_signal": "47.39",
      "bollinger_signal": "Nenhum",
      "macd_signal": "Nenhum",
      "mme_cross": "Nenhum",
      "market_cap": 84534
    }
  },
  {
    "timestamp": "2025-08-16T15:53:03.799740",
    "symbol": "ETHUSDT",
    "trigger": "Pre\u00e7o Acima de $3500.00 (Atual: $4409.05)",
    "data": {
      "symbol": "ETHUSDT",
      "current_price": 4409.05,
      "price_change_24h": -0.101,
      "volume_24h": 2165079637.86721,
      "rsi_value": 40.30155557486765,
      "rsi_signal": "40.30",
      "bollinger_signal": "Nenhum",
      "macd_signal": "Nenhum",
      "mme_cross": "Nenhum",
      "market_cap": 84551
    }
  },
  {
    "timestamp": "2025-08-16T15:46:18.335781",
    "symbol": "ETHUSDT",
    "trigger": "Pre\u00e7o Acima de $3500.00 (Atual: $4409.26)",
    "data": {
      "symbol": "ETHUSDT",
      "current_price": 4409.26,
      "price_change_24h": 0.238,
      "volume_24h": 2174029226.959555,
      "rsi_value": 40.353390639923724,
      "rsi_signal": "40.35",
      "bollinger_signal": "Nenhum",
      "macd_signal": "Nenhum",
      "mme_cross": "Nenhum",
      "market_cap": 84958
    }
  },
  {
    "timestamp": "2025-08-16T15:41:05.729726",
    "symbol": "ETHUSDT",
    "trigger": "Pre\u00e7o Acima de $3500.00 (Atual: $4411.37)",
    "data": {
      "symbol": "ETHUSDT",
      "current_price": 4411.37,
      "price_change_24h": -0.022,
      "volume_24h": 2186640403.867165,
      "rsi_value": 40.89481608948166,
      "rsi_signal": "40.89",
      "bollinger_signal": "Nenhum",
      "macd_signal": "Nenhum",
      "mme_cross": "Nenhum",
      "market_cap": 84141
    }
  },
  {
    "timestamp": "2025-08-16T15:36:02.561443",
    "symbol": "ETHUSDT",
    "trigger": "Pre\u00e7o Acima de $3500.00 (Atual: $4414.54)",
    "data": {
      "symbol": "ETHUSDT",
      "current_price": 4414.54,
      "price_change_24h": 0.01,
      "volume_24h": 2191261487.467159,
      "rsi_value": 41.5660088465465,
      "rsi_signal": "41.57",
      "bollinger_signal": "Nenhum",
      "macd_signal": "Nenhum",
      "mme_cross": "Nenhum",
      "market_cap": 85035
    }
  },
  {
    "timestamp": "2025-08-16T12:05:55.047918",
    "symbol": "ETHUSDT",
    "trigger": "Pre\u00e7o Acima de $3500.00 (Atual: $4414.53)",
    "data": {
      "symbol": "ETHUSDT",
      "current_price": 4414.53,
      "price_change_24h": -1.451,
      "volume_24h": 3041254178.788809,
      "rsi_value": 36.89045175643212,
      "rsi_signal": "36.89",
      "bollinger_signal": "Nenhum",
      "macd_signal": "Nenhum",
      "mme_cross": "Nenhum",
      "market_cap": 85803
    }
  },
  {
    "timestamp": "2025-08-16T12:00:52.046177",
    "symbol": "ETHUSDT",
    "trigger": "Pre\u00e7o Acima de $3500.00 (Atual: $4417.58)",
    "data": {
      "symbol": "ETHUSDT",
      "current_price": 4417.58,
      "price_change_24h": -1.534,
      "volume_24h": 3058509573.476451,
      "rsi_value": 37.50266505578865,
      "rsi_signal": "37.50",
      "bollinger_signal": "Nenhum",
      "macd_signal": "Nenhum",
      "mme_cross": "Nenhum",
      "market_cap": 85803
    }
  },
  {
    "timestamp": "2025-08-16T11:55:49.256566",
    "symbol": "ETHUSDT",
    "trigger": "Pre\u00e7o Acima de $3500.00 (Atual: $4413.16)",
    "data": {
      "symbol": "ETHUSDT",
      "current_price": 4413.16,
      "price_change_24h": -1.698,
      "volume_24h": 3117996077.739847,
      "rsi_value": 39.030055118383345,
      "rsi_signal": "39.03",
      "bollinger_signal": "Nenhum",
      "macd_signal": "Nenhum",
      "mme_cross": "Nenhum",
      "market_cap": 85398
    }
  },
  {
    "timestamp": "2025-08-16T11:50:46.336257",
    "symbol": "ETHUSDT",
    "trigger": "Pre\u00e7o Acima de $3500.00 (Atual: $4408.83)",
    "data": {
      "symbol": "ETHUSDT",
      "current_price": 4408.83,
      "price_change_24h": -2.273,
      "volume_24h": 3146520348.005968,
      "rsi_value": 38.17274229268481,
      "rsi_signal": "38.17",
      "bollinger_signal": "Nenhum",
      "macd_signal": "Nenhum",
      "mme_cross": "Nenhum",
      "market_cap": 85338
    }
  },
  {
    "timestamp": "2025-08-16T11:50:46.335766",
    "symbol": "ETHUSDT",
    "trigger": "Fuga de Capital (Vol > 1.00% Cap.Merc. e Var < -2.00%)",
    "data": {
      "symbol": "ETHUSDT",
      "current_price": 4408.83,
      "price_change_24h": -2.273,
      "volume_24h": 3146520348.005968,
      "rsi_value": 38.17274229268481,
      "rsi_signal": "38.17",
      "bollinger_signal": "Nenhum",
      "macd_signal": "Nenhum",
      "mme_cross": "Nenhum",
      "market_cap": 85338
    }
  },
  {
    "timestamp": "2025-08-16T11:45:43.007468",
    "symbol": "ETHUSDT",
    "trigger": "Pre\u00e7o Acima de $3500.00 (Atual: $4404.76)",
    "data": {
      "symbol": "ETHUSDT",
      "current_price": 4404.76,
      "price_change_24h": -2.657,
      "volume_24h": 3196738314.80016,
      "rsi_value": 37.187957572944,
      "rsi_signal": "37.19",
      "bollinger_signal": "Nenhum",
      "macd_signal": "Nenhum",
      "mme_cross": "Nenhum",
      "market_cap": 85757
    }
  },
  {
    "timestamp": "2025-08-16T11:45:43.006760",
    "symbol": "ETHUSDT",
    "trigger": "Fuga de Capital (Vol > 1.00% Cap.Merc. e Var < -2.00%)",
    "data": {
      "symbol": "ETHUSDT",
      "current_price": 4404.76,
      "price_change_24h": -2.657,
      "volume_24h": 3196738314.80016,
      "rsi_value": 37.187957572944,
      "rsi_signal": "37.19",
      "bollinger_signal": "Nenhum",
      "macd_signal": "Nenhum",
      "mme_cross": "Nenhum",
      "market_cap": 85757
    }
  },
  {
    "timestamp": "2025-08-16T11:40:40.160110",
    "symbol": "ETHUSDT",
    "trigger": "Pre\u00e7o Acima de $3500.00 (Atual: $4398.83)",
    "data": {
      "symbol": "ETHUSDT",
      "current_price": 4398.83,
      "price_change_24h": -3.403,
      "volume_24h": 3220180735.089537,
      "rsi_value": 35.84065954109383,
      "rsi_signal": "35.84",
      "bollinger_signal": "Nenhum",
      "macd_signal": "Nenhum",
      "mme_cross": "Nenhum",
      "market_cap": 85755
    }
  },
  {
    "timestamp": "2025-08-16T11:40:40.159436",
    "symbol": "ETHUSDT",
    "trigger": "Fuga de Capital (Vol > 1.00% Cap.Merc. e Var < -2.00%)",
    "data": {
      "symbol": "ETHUSDT",
      "current_price": 4398.83,
      "price_change_24h": -3.403,
      "volume_24h": 3220180735.089537,
      "rsi_value": 35.84065954109383,
      "rsi_signal": "35.84",
      "bollinger_signal": "Nenhum",
      "macd_signal": "Nenhum",
      "mme_cross": "Nenhum",
      "market_cap": 85755
    }
  },
  {
    "timestamp": "2025-08-16T11:35:36.826349",
    "symbol": "ETHUSDT",
    "trigger": "Pre\u00e7o Acima de $3500.00 (Atual: $4405.19)",
    "data": {
      "symbol": "ETHUSDT",
      "current_price": 4405.19,
      "price_change_24h": -3.094,
      "volume_24h": 3225699186.278728,
      "rsi_value": 37.30438812248272,
      "rsi_signal": "37.30",
      "bollinger_signal": "Nenhum",
      "macd_signal": "Nenhum",
      "mme_cross": "Nenhum",
      "market_cap": 85605
    }
  },
  {
    "timestamp": "2025-08-16T11:35:36.825677",
    "symbol": "ETHUSDT",
    "trigger": "Fuga de Capital (Vol > 1.00% Cap.Merc. e Var < -2.00%)",
    "data": {
      "symbol": "ETHUSDT",
      "current_price": 4405.19,
      "price_change_24h": -3.094,
      "volume_24h": 3225699186.278728,
      "rsi_value": 37.30438812248272,
      "rsi_signal": "37.30",
      "bollinger_signal": "Nenhum",
      "macd_signal": "Nenhum",
      "mme_cross": "Nenhum",
      "market_cap": 85605
    }
  },
  {
    "timestamp": "2025-08-16T11:30:33.844196",
    "symbol": "ETHUSDT",
    "trigger": "Pre\u00e7o Acima de $3500.00 (Atual: $4407.73)",
    "data": {
      "symbol": "ETHUSDT",
      "current_price": 4407.73,
      "price_change_24h": -3.04,
      "volume_24h": 3236198921.695328,
      "rsi_value": 37.688655849217206,
      "rsi_signal": "37.69",
      "bollinger_signal": "Nenhum",
      "macd_signal": "Nenhum",
      "mme_cross": "Nenhum",
      "market_cap": 84925
    }
  },
  {
    "timestamp": "2025-08-16T11:30:33.843719",
    "symbol": "ETHUSDT",
    "trigger": "Fuga de Capital (Vol > 1.00% Cap.Merc. e Var < -2.00%)",
    "data": {
      "symbol": "ETHUSDT",
      "current_price": 4407.73,
      "price_change_24h": -3.04,
      "volume_24h": 3236198921.695328,
      "rsi_value": 37.688655849217206,
      "rsi_signal": "37.69",
      "bollinger_signal": "Nenhum",
      "macd_signal": "Nenhum",
      "mme_cross": "Nenhum",
      "market_cap": 84925
    }
  },
  {
    "timestamp": "2025-08-16T11:25:30.887779",
    "symbol": "ETHUSDT",
    "trigger": "Pre\u00e7o Acima de $3500.00 (Atual: $4400.51)",
    "data": {
      "symbol": "ETHUSDT",
      "current_price": 4400.51,
      "price_change_24h": -3.217,
      "volume_24h": 3242766958.320994,
      "rsi_value": 35.92247158262923,
      "rsi_signal": "35.92",
      "bollinger_signal": "Nenhum",
      "macd_signal": "Nenhum",
      "mme_cross": "Nenhum",
      "market_cap": 85441
    }
  },
  {
    "timestamp": "2025-08-16T11:25:30.887308",
    "symbol": "ETHUSDT",
    "trigger": "Fuga de Capital (Vol > 1.00% Cap.Merc. e Var < -2.00%)",
    "data": {
      "symbol": "ETHUSDT",
      "current_price": 4400.51,
      "price_change_24h": -3.217,
      "volume_24h": 3242766958.320994,
      "rsi_value": 35.92247158262923,
      "rsi_signal": "35.92",
      "bollinger_signal": "Nenhum",
      "macd_signal": "Nenhum",
      "mme_cross": "Nenhum",
      "market_cap": 85441
    }
  },
  {
    "timestamp": "2025-08-16T11:20:26.487833",
    "symbol": "ETHUSDT",
    "trigger": "Pre\u00e7o Acima de $3500.00 (Atual: $4398.82)",
    "data": {
      "symbol": "ETHUSDT",
      "current_price": 4398.82,
      "price_change_24h": -3.615,
      "volume_24h": 3260433117.570321,
      "rsi_value": 35.84065954109383,
      "rsi_signal": "35.84",
      "bollinger_signal": "Nenhum",
      "macd_signal": "Nenhum",
      "mme_cross": "Nenhum",
      "market_cap": 85341
    }
  },
  {
    "timestamp": "2025-08-16T11:20:26.487286",
    "symbol": "ETHUSDT",
    "trigger": "Fuga de Capital (Vol > 1.00% Cap.Merc. e Var < -2.00%)",
    "data": {
      "symbol": "ETHUSDT",
      "current_price": 4398.82,
      "price_change_24h": -3.615,
      "volume_24h": 3260433117.570321,
      "rsi_value": 35.84065954109383,
      "rsi_signal": "35.84",
      "bollinger_signal": "Nenhum",
      "macd_signal": "Nenhum",
      "mme_cross": "Nenhum",
      "market_cap": 85341
    }
  },
  {
    "timestamp": "2025-08-16T11:15:23.560628",
    "symbol": "ETHUSDT",
    "trigger": "Pre\u00e7o Acima de $3500.00 (Atual: $4401.38)",
    "data": {
      "symbol": "ETHUSDT",
      "current_price": 4401.38,
      "price_change_24h": -3.606,
      "volume_24h": 3291466987.634724,
      "rsi_value": 36.59697188175945,
      "rsi_signal": "36.60",
      "bollinger_signal": "Nenhum",
      "macd_signal": "Nenhum",
      "mme_cross": "Nenhum",
      "market_cap": 85014
    }
  },
  {
    "timestamp": "2025-08-16T11:15:23.560176",
    "symbol": "ETHUSDT",
    "trigger": "Fuga de Capital (Vol > 1.00% Cap.Merc. e Var < -2.00%)",
    "data": {
      "symbol": "ETHUSDT",
      "current_price": 4401.38,
      "price_change_24h": -3.606,
      "volume_24h": 3291466987.634724,
      "rsi_value": 36.59697188175945,
      "rsi_signal": "36.60",
      "bollinger_signal": "Nenhum",
      "macd_signal": "Nenhum",
      "mme_cross": "Nenhum",
      "market_cap": 85014
    }
  },
  {
    "timestamp": "2025-08-16T11:10:20.187724",
    "symbol": "ETHUSDT",
    "trigger": "Pre\u00e7o Acima de $3500.00 (Atual: $4396.83)",
    "data": {
      "symbol": "ETHUSDT",
      "current_price": 4396.83,
      "price_change_24h": -3.651,
      "volume_24h": 3303013278.374859,
      "rsi_value": 35.38337190932832,
      "rsi_signal": "35.38",
      "bollinger_signal": "Nenhum",
      "macd_signal": "Nenhum",
      "mme_cross": "Nenhum",
      "market_cap": 84954
    }
  },
  {
    "timestamp": "2025-08-16T11:10:20.187160",
    "symbol": "ETHUSDT",
    "trigger": "Fuga de Capital (Vol > 1.00% Cap.Merc. e Var < -2.00%)",
    "data": {
      "symbol": "ETHUSDT",
      "current_price": 4396.83,
      "price_change_24h": -3.651,
      "volume_24h": 3303013278.374859,
      "rsi_value": 35.38337190932832,
      "rsi_signal": "35.38",
      "bollinger_signal": "Nenhum",
      "macd_signal": "Nenhum",
      "mme_cross": "Nenhum",
      "market_cap": 84954
    }
  },
  {
    "timestamp": "2025-08-16T11:05:16.190059",
    "symbol": "ETHUSDT",
    "trigger": "Pre\u00e7o Acima de $3500.00 (Atual: $4397.01)",
    "data": {
      "symbol": "ETHUSDT",
      "current_price": 4397.01,
      "price_change_24h": -3.629,
      "volume_24h": 3323963464.136835,
      "rsi_value": 35.414218566392776,
      "rsi_signal": "35.41",
      "bollinger_signal": "Nenhum",
      "macd_signal": "Nenhum",
      "mme_cross": "Nenhum",
      "market_cap": 85449
    }
  },
  {
    "timestamp": "2025-08-16T11:05:16.189527",
    "symbol": "ETHUSDT",
    "trigger": "Fuga de Capital (Vol > 1.00% Cap.Merc. e Var < -2.00%)",
    "data": {
      "symbol": "ETHUSDT",
      "current_price": 4397.01,
      "price_change_24h": -3.629,
      "volume_24h": 3323963464.136835,
      "rsi_value": 35.414218566392776,
      "rsi_signal": "35.41",
      "bollinger_signal": "Nenhum",
      "macd_signal": "Nenhum",
      "mme_cross": "Nenhum",
      "market_cap": 85449
    }
  },
  {
    "timestamp": "2025-08-16T11:00:13.284914",
    "symbol": "ETHUSDT",
    "trigger": "Pre\u00e7o Acima de $3500.00 (Atual: $4392.50)",
    "data": {
      "symbol": "ETHUSDT",
      "current_price": 4392.5,
      "price_change_24h": -3.088,
      "volume_24h": 3373286167.639857,
      "rsi_value": 34.48772383237977,
      "rsi_signal": "34.49",
      "bollinger_signal": "Nenhum",
      "macd_signal": "Nenhum",
      "mme_cross": "Nenhum",
      "market_cap": 85213
    }
  },
  {
    "timestamp": "2025-08-16T11:00:13.284568",
    "symbol": "ETHUSDT",
    "trigger": "Fuga de Capital (Vol > 1.00% Cap.Merc. e Var < -2.00%)",
    "data": {
      "symbol": "ETHUSDT",
      "current_price": 4392.5,
      "price_change_24h": -3.088,
      "volume_24h": 3373286167.639857,
      "rsi_value": 34.48772383237977,
      "rsi_signal": "34.49",
      "bollinger_signal": "Nenhum",
      "macd_signal": "Nenhum",
      "mme_cross": "Nenhum",
      "market_cap": 85213
    }
  },
  {
    "timestamp": "2025-08-16T10:55:10.217757",
    "symbol": "ETHUSDT",
    "trigger": "Pre\u00e7o Acima de $3500.00 (Atual: $4396.56)",
    "data": {
      "symbol": "ETHUSDT",
      "current_price": 4396.56,
      "price_change_24h": -3.192,
      "volume_24h": 3392558265.226584,
      "rsi_value": 42.93664383561642,
      "rsi_signal": "42.94",
      "bollinger_signal": "Nenhum",
      "macd_signal": "Nenhum",
      "mme_cross": "Nenhum",
      "market_cap": 85244
    }
  },
  {
    "timestamp": "2025-08-16T10:55:10.217262",
    "symbol": "ETHUSDT",
    "trigger": "Fuga de Capital (Vol > 1.00% Cap.Merc. e Var < -2.00%)",
    "data": {
      "symbol": "ETHUSDT",
      "current_price": 4396.56,
      "price_change_24h": -3.192,
      "volume_24h": 3392558265.226584,
      "rsi_value": 42.93664383561642,
      "rsi_signal": "42.94",
      "bollinger_signal": "Nenhum",
      "macd_signal": "Nenhum",
      "mme_cross": "Nenhum",
      "market_cap": 85244
    }
  },
  {
    "timestamp": "2025-08-16T10:50:07.236935",
    "symbol": "ETHUSDT",
    "trigger": "Pre\u00e7o Acima de $3500.00 (Atual: $4386.90)",
    "data": {
      "symbol": "ETHUSDT",
      "current_price": 4386.9,
      "price_change_24h": -3.745,
      "volume_24h": 3423300065.3301,
      "rsi_value": 41.61161640338278,
      "rsi_signal": "41.61",
      "bollinger_signal": "Nenhum",
      "macd_signal": "Nenhum",
      "mme_cross": "Nenhum",
      "market_cap": 84862
    }
  },
  {
    "timestamp": "2025-08-16T10:50:07.236456",
    "symbol": "ETHUSDT",
    "trigger": "Fuga de Capital (Vol > 1.00% Cap.Merc. e Var < -2.00%)",
    "data": {
      "symbol": "ETHUSDT",
      "current_price": 4386.9,
      "price_change_24h": -3.745,
      "volume_24h": 3423300065.3301,
      "rsi_value": 41.61161640338278,
      "rsi_signal": "41.61",
      "bollinger_signal": "Nenhum",
      "macd_signal": "Nenhum",
      "mme_cross": "Nenhum",
      "market_cap": 84862
    }
  },
  {
    "timestamp": "2025-08-16T10:45:04.367653",
    "symbol": "ETHUSDT",
    "trigger": "Pre\u00e7o Acima de $3500.00 (Atual: $4399.44)",
    "data": {
      "symbol": "ETHUSDT",
      "current_price": 4399.44,
      "price_change_24h": -3.568,
      "volume_24h": 3437079476.430215,
      "rsi_value": 43.3780232209987,
      "rsi_signal": "43.38",
      "bollinger_signal": "Nenhum",
      "macd_signal": "Nenhum",
      "mme_cross": "Nenhum",
      "market_cap": 84867
    }
  },
  {
    "timestamp": "2025-08-16T10:45:04.367143",
    "symbol": "ETHUSDT",
    "trigger": "Fuga de Capital (Vol > 1.00% Cap.Merc. e Var < -2.00%)",
    "data": {
      "symbol": "ETHUSDT",
      "current_price": 4399.44,
      "price_change_24h": -3.568,
      "volume_24h": 3437079476.430215,
      "rsi_value": 43.3780232209987,
      "rsi_signal": "43.38",
      "bollinger_signal": "Nenhum",
      "macd_signal": "Nenhum",
      "mme_cross": "Nenhum",
      "market_cap": 84867
    }
  },
  {
    "timestamp": "2025-08-16T10:40:00.134424",
    "symbol": "ETHUSDT",
    "trigger": "Pre\u00e7o Acima de $3500.00 (Atual: $4407.90)",
    "data": {
      "symbol": "ETHUSDT",
      "current_price": 4407.9,
      "price_change_24h": -3.867,
      "volume_24h": 3454883961.352159,
      "rsi_value": 44.65563889174291,
      "rsi_signal": "44.66",
      "bollinger_signal": "Nenhum",
      "macd_signal": "Nenhum",
      "mme_cross": "Nenhum",
      "market_cap": 85243
    }
  },
  {
    "timestamp": "2025-08-16T10:40:00.134083",
    "symbol": "ETHUSDT",
    "trigger": "Fuga de Capital (Vol > 1.00% Cap.Merc. e Var < -2.00%)",
    "data": {
      "symbol": "ETHUSDT",
      "current_price": 4407.9,
      "price_change_24h": -3.867,
      "volume_24h": 3454883961.352159,
      "rsi_value": 44.65563889174291,
      "rsi_signal": "44.66",
      "bollinger_signal": "Nenhum",
      "macd_signal": "Nenhum",
      "mme_cross": "Nenhum",
      "market_cap": 85243
    }
  },
  {
    "timestamp": "2025-08-16T10:34:57.039635",
    "symbol": "ETHUSDT",
    "trigger": "Pre\u00e7o Acima de $3500.00 (Atual: $4415.76)",
    "data": {
      "symbol": "ETHUSDT",
      "current_price": 4415.76,
      "price_change_24h": -4.129,
      "volume_24h": 3492587098.882305,
      "rsi_value": 45.99235996078567,
      "rsi_signal": "45.99",
      "bollinger_signal": "Nenhum",
      "macd_signal": "Nenhum",
      "mme_cross": "Nenhum",
      "market_cap": 85243
    }
  },
  {
    "timestamp": "2025-08-16T10:34:57.039321",
    "symbol": "ETHUSDT",
    "trigger": "Fuga de Capital (Vol > 1.00% Cap.Merc. e Var < -2.00%)",
    "data": {
      "symbol": "ETHUSDT",
      "current_price": 4415.76,
      "price_change_24h": -4.129,
      "volume_24h": 3492587098.882305,
      "rsi_value": 45.99235996078567,
      "rsi_signal": "45.99",
      "bollinger_signal": "Nenhum",
      "macd_signal": "Nenhum",
      "mme_cross": "Nenhum",
      "market_cap": 85243
    }
  },
  {
    "timestamp": "2025-08-16T10:29:54.592142",
    "symbol": "ETHUSDT",
    "trigger": "Pre\u00e7o Acima de $3500.00 (Atual: $4421.12)",
    "data": {
      "symbol": "ETHUSDT",
      "current_price": 4421.12,
      "price_change_24h": -4.198,
      "volume_24h": 3507770064.021301,
      "rsi_value": 46.835274542429225,
      "rsi_signal": "46.84",
      "bollinger_signal": "Nenhum",
      "macd_signal": "Nenhum",
      "mme_cross": "Nenhum",
      "market_cap": 85007
    }
  },
  {
    "timestamp": "2025-08-16T10:29:54.591617",
    "symbol": "ETHUSDT",
    "trigger": "Fuga de Capital (Vol > 1.00% Cap.Merc. e Var < -2.00%)",
    "data": {
      "symbol": "ETHUSDT",
      "current_price": 4421.12,
      "price_change_24h": -4.198,
      "volume_24h": 3507770064.021301,
      "rsi_value": 46.835274542429225,
      "rsi_signal": "46.84",
      "bollinger_signal": "Nenhum",
      "macd_signal": "Nenhum",
      "mme_cross": "Nenhum",
      "market_cap": 85007
    }
  },
  {
    "timestamp": "2025-08-16T10:24:51.743240",
    "symbol": "ETHUSDT",
    "trigger": "Pre\u00e7o Acima de $3500.00 (Atual: $4417.20)",
    "data": {
      "symbol": "ETHUSDT",
      "current_price": 4417.2,
      "price_change_24h": -4.315,
      "volume_24h": 3511944972.201145,
      "rsi_value": 46.253994953742584,
      "rsi_signal": "46.25",
      "bollinger_signal": "Nenhum",
      "macd_signal": "Nenhum",
      "mme_cross": "Nenhum",
      "market_cap": 84855
    }
  },
  {
    "timestamp": "2025-08-16T10:07:50.939724",
    "symbol": "ETHUSDT",
    "trigger": "Pre\u00e7o Acima de $3500.00 (Atual: $4417.92)",
    "data": {
      "symbol": "ETHUSDT",
      "current_price": 4417.92,
      "price_change_24h": -4.425,
      "volume_24h": 3544899776.020012,
      "rsi_value": 46.52205931579291,
      "rsi_signal": "46.52",
      "bollinger_signal": "Nenhum",
      "macd_signal": "Nenhum",
      "mme_cross": "Nenhum",
      "market_cap": 84476
    }
  },
  {
    "timestamp": "2025-08-16T08:27:40.766177",
    "symbol": "ETHUSDT",
    "trigger": "Pre\u00e7o Acima de $3500.00 (Atual: $4407.91)",
    "data": {
      "symbol": "ETHUSDT",
      "current_price": 4407.91,
      "price_change_24h": -4.756,
      "volume_24h": 3699204926.810216,
      "rsi_value": 46.93078702330826,
      "rsi_signal": "46.93",
      "bollinger_signal": "Nenhum",
      "macd_signal": "Nenhum",
      "mme_cross": "Nenhum",
      "market_cap": 84356
    }
  },
  {
    "timestamp": "2025-07-30T18:15:45.115523",
    "symbol": "ETHUSDT",
    "trigger": "Pre\u00e7o Acima de $3500.00 (Atual: $3765.32)",
    "data": {
      "symbol": "ETHUSDT",
      "current_price": 3765.32,
      "price_change_24h": -0.051,
      "volume_24h": 1927238160.546767,
      "rsi_value": 41.70761000109179,
      "rsi_signal": "41.71",
      "bollinger_signal": "Nenhum",
      "macd_signal": "Nenhum",
      "mme_cross": "Nenhum",
      "market_cap": 59539
    }
  },
  {
    "timestamp": "2025-07-30T18:10:42.400644",
    "symbol": "ETHUSDT",
    "trigger": "Pre\u00e7o Acima de $3500.00 (Atual: $3768.56)",
    "data": {
      "symbol": "ETHUSDT",
      "current_price": 3768.56,
      "price_change_24h": 0.095,
      "volume_24h": 1928432282.949805,
      "rsi_value": 42.11996471625991,
      "rsi_signal": "42.12",
      "bollinger_signal": "Nenhum",
      "macd_signal": "Nenhum",
      "mme_cross": "Nenhum",
      "market_cap": 59859
    }
  },
  {
    "timestamp": "2025-07-30T18:05:54.815339",
    "symbol": "ETHUSDT",
    "trigger": "Pre\u00e7o Acima de $3500.00 (Atual: $3768.62)",
    "data": {
      "symbol": "ETHUSDT",
      "current_price": 3768.62,
      "price_change_24h": 0.3,
      "volume_24h": 1932252909.83469,
      "rsi_value": 42.12925520182337,
      "rsi_signal": "42.13",
      "bollinger_signal": "Nenhum",
      "macd_signal": "Nenhum",
      "mme_cross": "Nenhum",
      "market_cap": 59507
    }
  },
  {
    "timestamp": "2025-07-30T17:48:12.148012",
    "symbol": "ETHUSDT",
    "trigger": "Pre\u00e7o Acima de $3500.00 (Atual: $3767.07)",
    "data": {
      "symbol": "ETHUSDT",
      "current_price": 3767.07,
      "price_change_24h": 0.342,
      "volume_24h": 1932612690.084934,
      "rsi_value": 39.66422575459905,
      "rsi_signal": "39.66",
      "bollinger_signal": "Nenhum",
      "macd_signal": "Nenhum",
      "mme_cross": "Nenhum",
      "market_cap": 59475
    }
  },
  {
    "timestamp": "2025-07-30T17:43:09.372769",
    "symbol": "ETHUSDT",
    "trigger": "Pre\u00e7o Acima de $3500.00 (Atual: $3775.44)",
    "data": {
      "symbol": "ETHUSDT",
      "current_price": 3775.44,
      "price_change_24h": 0.65,
      "volume_24h": 1931276494.861901,
      "rsi_value": 41.34662129314541,
      "rsi_signal": "41.35",
      "bollinger_signal": "Nenhum",
      "macd_signal": "Nenhum",
      "mme_cross": "Nenhum",
      "market_cap": 59652
    }
  },
  {
    "timestamp": "2025-07-30T17:34:19.922704",
    "symbol": "ETHUSDT",
    "trigger": "Pre\u00e7o Acima de $3500.00 (Atual: $3770.12)",
    "data": {
      "symbol": "ETHUSDT",
      "current_price": 3770.12,
      "price_change_24h": 0.519,
      "volume_24h": 1933965553.304014,
      "rsi_value": 40.312378529276664,
      "rsi_signal": "40.31",
      "bollinger_signal": "Nenhum",
      "macd_signal": "Nenhum",
      "mme_cross": "Nenhum",
      "market_cap": 59730
    }
  },
  {
    "timestamp": "2025-07-30T17:29:17.422617",
    "symbol": "ETHUSDT",
    "trigger": "Pre\u00e7o Acima de $3500.00 (Atual: $3772.75)",
    "data": {
      "symbol": "ETHUSDT",
      "current_price": 3772.75,
      "price_change_24h": 0.138,
      "volume_24h": 1936145991.537643,
      "rsi_value": 40.83712784588447,
      "rsi_signal": "40.84",
      "bollinger_signal": "Nenhum",
      "macd_signal": "Nenhum",
      "mme_cross": "Nenhum",
      "market_cap": 60075
    }
  },
  {
    "timestamp": "2025-07-30T15:05:27.932582",
    "symbol": "ETHUSDT",
    "trigger": "Pre\u00e7o Acima de $3500.00 (Atual: $3798.01)",
    "data": {
      "symbol": "ETHUSDT",
      "current_price": 3798.01,
      "price_change_24h": 0.951,
      "volume_24h": 1557226592.47222,
      "rsi_value": 47.04060236370565,
      "rsi_signal": "47.04",
      "bollinger_signal": "Nenhum",
      "macd_signal": "Nenhum",
      "mme_cross": "Nenhum",
      "market_cap": 63869
    }
  },
  {
    "timestamp": "2025-07-30T15:00:25.453566",
    "symbol": "ETHUSDT",
    "trigger": "Pre\u00e7o Acima de $3500.00 (Atual: $3813.14)",
    "data": {
      "symbol": "ETHUSDT",
      "current_price": 3813.14,
      "price_change_24h": 1.189,
      "volume_24h": 1535141065.201419,
      "rsi_value": 51.43359802196752,
      "rsi_signal": "51.43",
      "bollinger_signal": "Nenhum",
      "macd_signal": "Nenhum",
      "mme_cross": "Nenhum",
      "market_cap": 64072
    }
  },
  {
    "timestamp": "2025-07-26T21:31:07.161892",
    "symbol": "ETHUSDT",
    "trigger": "Pre\u00e7o Acima de $3500.00 (Atual: $3741.05)",
    "data": {
      "symbol": "ETHUSDT",
      "current_price": 3741.05,
      "price_change_24h": 0.454,
      "volume_24h": 1525470845.670226,
      "rsi_value": 42.212518195051,
      "rsi_signal": "42.21",
      "bollinger_signal": "Nenhum",
      "macd_signal": "Nenhum",
      "mme_cross": "Nenhum",
      "market_cap": 62758
    }
  },
  {
    "timestamp": "2025-07-26T21:26:06.012267",
    "symbol": "ETHUSDT",
    "trigger": "Pre\u00e7o Acima de $3500.00 (Atual: $3740.00)",
    "data": {
      "symbol": "ETHUSDT",
      "current_price": 3740.0,
      "price_change_24h": 0.419,
      "volume_24h": 1526052796.337693,
      "rsi_value": 41.98841698841709,
      "rsi_signal": "41.99",
      "bollinger_signal": "Nenhum",
      "macd_signal": "Nenhum",
      "mme_cross": "Nenhum",
      "market_cap": 62737
    }
  },
  {
    "timestamp": "2025-07-26T19:59:35.503697",
    "symbol": "ETHUSDT",
    "trigger": "Pre\u00e7o Acima de $3500.00 (Atual: $3750.41)",
    "data": {
      "symbol": "ETHUSDT",
      "current_price": 3750.41,
      "price_change_24h": 0.805,
      "volume_24h": 1537196715.791241,
      "rsi_value": 44.92164337145266,
      "rsi_signal": "44.92",
      "bollinger_signal": "Nenhum",
      "macd_signal": "Nenhum",
      "mme_cross": "Nenhum",
      "market_cap": 62892
    }
  },
  {
    "timestamp": "2025-07-26T19:24:10.156697",
    "symbol": "SOLUSDT",
    "trigger": "Pre\u00e7o Abaixo de $299.00 (Atual: $186.41)",
    "data": {
      "symbol": "SOLUSDT",
      "current_price": 186.41,
      "price_change_24h": 0.621,
      "volume_24h": 336168166.97877,
      "rsi_value": 41.13636363636358,
      "rsi_signal": "41.14",
      "bollinger_signal": "Nenhum",
      "macd_signal": "Nenhum",
      "mme_cross": "Nenhum",
      "market_cap": 0.0
    }
  },
  {
    "timestamp": "2025-07-26T19:24:09.735777",
    "symbol": "ETHUSDT",
    "trigger": "Pre\u00e7o Acima de $3500.00 (Atual: $3778.60)",
    "data": {
      "symbol": "ETHUSDT",
      "current_price": 3778.6,
      "price_change_24h": 1.616,
      "volume_24h": 1486645760.953261,
      "rsi_value": 56.16153846153848,
      "rsi_signal": "56.16",
      "bollinger_signal": "Acima da Banda",
      "macd_signal": "Cruzamento de Alta",
      "mme_cross": "Nenhum",
      "market_cap": 63063
    }
  },
  {
    "timestamp": "2025-07-26T19:20:32.757966",
    "symbol": "SOLUSDT",
    "trigger": "Pre\u00e7o Abaixo de $299.00 (Atual: $186.23)",
    "data": {
      "symbol": "SOLUSDT",
      "current_price": 186.23,
      "price_change_24h": 0.496,
      "volume_24h": 335109253.96793,
      "rsi_value": 40.181611804767336,
      "rsi_signal": "40.18",
      "bollinger_signal": "Nenhum",
      "macd_signal": "Nenhum",
      "mme_cross": "Nenhum",
      "market_cap": 0.0
    }
  },
  {
    "timestamp": "2025-07-26T19:20:32.139717",
    "symbol": "ETHUSDT",
    "trigger": "Pre\u00e7o Acima de $3500.00 (Atual: $3763.20)",
    "data": {
      "symbol": "ETHUSDT",
      "current_price": 3763.2,
      "price_change_24h": 1.218,
      "volume_24h": 1460549597.853445,
      "rsi_value": 52.65038218677307,
      "rsi_signal": "52.65",
      "bollinger_signal": "Nenhum",
      "macd_signal": "Nenhum",
      "mme_cross": "Nenhum",
      "market_cap": 62771
    }
  },
  {
    "timestamp": "2025-07-26T19:17:05.790355",
    "symbol": "SOLUSDT",
    "trigger": "Pre\u00e7o Abaixo de $299.00 (Atual: $185.92)",
    "data": {
      "symbol": "SOLUSDT",
      "current_price": 185.92,
      "price_change_24h": 0.313,
      "volume_24h": 335003148.79278,
      "rsi_value": 38.688524590163944,
      "rsi_signal": "38.69",
      "bollinger_signal": "Nenhum",
      "macd_signal": "Nenhum",
      "mme_cross": "Nenhum",
      "market_cap": 0.0
    }
  },
  {
    "timestamp": "2025-07-26T19:17:05.329516",
    "symbol": "ETHUSDT",
    "trigger": "Pre\u00e7o Acima de $3500.00 (Atual: $3756.42)",
    "data": {
      "symbol": "ETHUSDT",
      "current_price": 3756.42,
      "price_change_24h": 0.997,
      "volume_24h": 1460851558.586373,
      "rsi_value": 47.18811176365893,
      "rsi_signal": "47.19",
      "bollinger_signal": "Nenhum",
      "macd_signal": "Nenhum",
      "mme_cross": "Nenhum",
      "market_cap": 62832
    }
  },
  {
    "timestamp": "2025-07-26T19:14:41.309406",
    "symbol": "SOLUSDT",
    "trigger": "Pre\u00e7o Abaixo de $299.00 (Atual: $186.19)",
    "data": {
      "symbol": "SOLUSDT",
      "current_price": 186.19,
      "price_change_24h": 0.372,
      "volume_24h": 335613804.13359,
      "rsi_value": 39.820022497187814,
      "rsi_signal": "39.82",
      "bollinger_signal": "Nenhum",
      "macd_signal": "Nenhum",
      "mme_cross": "Nenhum",
      "market_cap": 0.0
    }
  },
  {
    "timestamp": "2025-07-26T19:14:12.998494",
    "symbol": "ETHUSDT",
    "trigger": "Pre\u00e7o Acima de $3500.00 (Atual: $3760.60)",
    "data": {
      "symbol": "ETHUSDT",
      "current_price": 3760.6,
      "price_change_24h": 0.986,
      "volume_24h": 1465551099.388579,
      "rsi_value": 49.043276108726815,
      "rsi_signal": "49.04",
      "bollinger_signal": "Nenhum",
      "macd_signal": "Nenhum",
      "mme_cross": "Nenhum",
      "market_cap": 62832
    }
  },
  {
    "timestamp": "2025-07-26T19:11:07.754896",
    "symbol": "SOLUSDT",
    "trigger": "Pre\u00e7o Abaixo de $299.00 (Atual: $186.51)",
    "data": {
      "symbol": "SOLUSDT",
      "current_price": 186.51,
      "price_change_24h": 0.773,
      "volume_24h": 335280640.08854,
      "rsi_value": 41.60090191657262,
      "rsi_signal": "41.60",
      "bollinger_signal": "Nenhum",
      "macd_signal": "Nenhum",
      "mme_cross": "Nenhum",
      "market_cap": 0.0
    }
  },
  {
    "timestamp": "2025-07-26T19:10:43.593775",
    "symbol": "ETHUSDT",
    "trigger": "Pre\u00e7o Acima de $3500.00 (Atual: $3760.69)",
    "data": {
      "symbol": "ETHUSDT",
      "current_price": 3760.69,
      "price_change_24h": 1.095,
      "volume_24h": 1465743302.774183,
      "rsi_value": 49.20224618949997,
      "rsi_signal": "49.20",
      "bollinger_signal": "Nenhum",
      "macd_signal": "Nenhum",
      "mme_cross": "Nenhum",
      "market_cap": 63219
    }
  }
]